Workbook

Sheet How to Use
B2: AI Governance Playbook & Runbook
B3: An operating manual for managing AI risk across the lifecycle — built for a MAS-regulated financial institution.
B6: What this is
B7: Purpose | C7: Turns the ISO 42001 / NIST AI RMF / MAS control sets into something a team runs day-to-day: defined roles, lifecycle plays with step-by-step runbooks, living control trackers, a stress-test tracker, and a maturity dashboard.
B9: The tabs, and how they connect
B10: Roles & RACI | C10: Defines who does what, on a three-lines-of-defence model. Every play and control references these roles. Start here — ownership is the spine of the playbook.
B11: Playbooks & Runbooks | C11: 10 lifecycle plays (intake -> impact assessment -> validation -> deployment -> monitoring -> incident -> third-party -> review -> decommission -> stress-test). Each play has a trigger, owner, ordered steps, evidence, and the controls it satisfies.
B12: Control Library (ISO / NIST / MAS) | C12: The full control catalogues, now as trackers: assign an owner, set status & maturity, record evidence and review dates. These are the 'what'; the plays are the 'how'.
B13: Stress-Test Tracker | C13: The hotspot register (10 core + SAFR runtime) as a live test register: owner, cadence, last run, result, residual risk, next run.
B14: Maturity Dashboard | C14: Rolls up status and maturity across the control library so you can see readiness at a glance and report it upward.
B16: Suggested operating cadence
B17: On every new AI use-case | C17: Run Play 1 (Intake & Triage). Materiality decides how much of Plays 2-4 apply.
B18: Continuously / monthly | C18: Play 5 (Monitoring); review Stress-Test Tracker items due.
B19: On event | C19: Play 6 (Incident), Play 7 (Third-party onboarding / vendor change), Play 9 (Decommission).
B20: Quarterly | C20: Play 10 (Stress-test cycle); refresh Maturity Dashboard; AI Risk Committee review.
B21: Annually / on material change | C21: Play 8 (Periodic review & re-validation); refresh AI policy (ISO A.2.4).
B23: How to use the trackers
B24: Dropdowns | C24: Status, Maturity (1-5), test Result and Residual risk are dropdown cells — pick from the list. The dashboard reads these automatically.
B25: Owners | C25: Default owner roles are pre-filled as a starting point; reassign to named individuals/teams for your org.
B26: Caveat | C26: Control text is a working summary, not verbatim standard wording. MAS AIRG is a proposed guideline (Consultation Paper P017-2025, Nov 2025); public consultation closed 31 Jan 2026, with a 12-month transition period running from the eventual issuance date — it is not yet in force. Calibrate cadence and gates to your own risk appetite and MAS supervisory expectations.
A28: Update — IMDA MGF for Agentic AI
B29: Control Library - MGF Agentic | C29: 34 agentic-AI controls (4 MGF dimensions) as a tracker, with Weight & Weighted-maturity columns and links to the plays. Feeds the dashboard alongside ISO/NIST/MAS.
B30: Play 11 — Agentic Operation & Human Oversight | C30: New play housing the agent-specific runtime practices (end-user disclosure & training, automation-bias monitoring, red-team review) that don't fit the model-lifecycle plays.
A31: Update — FEAT operationalised
C32: FEAT (F1-F4) is now wired into the operating cadence: assessed in Play 2, gated in Plays 3/4, re-assessed in Plays 5/8, per the FEAT Assessment Methodology (Veritas-aligned) which defines the fairness/ethics/transparency assessments and high-materiality model validation.
A33: Update — MAS SAFR (Runtime safeguards)
B34: Control Library - SAFR | C34: 21 runtime safeguards across the 4 SAFR principles as a tracker — feeds the dashboard alongside ISO/NIST/MAS/MGF. The runtime companion to the MGF agentic controls (mapped to MAS AIRG, ISO 42001 and NIST AI RMF).
B35: Operationalised at the point of action | C35: Most SAFR controls link to Play 11 (Agentic Operation & Human Oversight), with mandate/design in Play 3, monitoring in Play 5 and third-party agents in Play 7.
B37: Prepared by | C37: Wu Yen Ching / wuyenching087@gmail.com
B38: Date | C38: June 2026
B39: Classification | C39: Proprietary & Confidential

Sheet Roles & RACI
A1: Roles & Responsibilities (Three Lines of Defence)
A3: Line | B3: Role | C3: Core responsibilities in AI governance | D3: RACI emphasis
A4: Board / Board Risk Cttee | B4: Board | C4: Ultimate accountability for AI risk; approves AI risk appetite & policy; oversees that management runs an effective AI risk framework. | D4: Accountable (appetite, policy)
A5: Senior Mgmt | B5: AI Risk / Model Governance Committee | C5: Owns the AI risk management framework; approves high-materiality use-cases and risk acceptances; reviews monitoring & incident reporting. | D5: Accountable (high-materiality go/no-go)
A6: 1st line | B6: Business / Model Owner | C6: Owns the use-case and its outcomes; accountable for intended use, risk acceptance at unit level, and day-to-day operation. | D6: Responsible / Accountable (use-case)
A7: 1st line | B7: Model Developer / Data Science | C7: Designs, builds, documents and tests the model; implements responsible-AI design requirements. | D7: Responsible (build, document)
A8: 1st line | B8: Data Owner / Steward | C8: Accountable for data quality, representativeness, lineage, provenance and data rights for AI. | D8: Responsible (data)
A9: 2nd line | B9: AI Risk / Model Risk Mgmt | C9: Independent oversight; sets materiality methodology, maintains framework & inventory standards, challenges 1st line. | D9: Responsible (oversight, triage)
A10: 2nd line | B10: Independent Validation | C10: Validates models independently of developers; issues validation opinion before deployment and at re-validation. | D10: Responsible (validation)
A11: 2nd line | B11: Compliance & Legal | C11: Maps regulatory obligations (MAS, PDPA, EU AI Act); reviews disclosures and external reporting. | D11: Consulted (regulatory)
A12: 2nd line | B12: Data Protection Officer | C12: Owns privacy impact (DPIA) and personal-data handling for AI systems. | D12: Consulted (privacy)
A13: 2nd line | B13: InfoSec / Cybersecurity | C13: AI-specific security, red-teaming, adversarial testing and technology controls. | D13: Responsible (security testing)
A14: 3rd line | B14: Internal Audit | C14: Independent assurance over the AI governance framework and its operation; not involved in design/run. | D14: Consulted / Informed (assurance)

Sheet Playbooks & Runbooks
A1: AI Governance Playbooks & Runbooks — 10 Lifecycle Plays
A2: Each play opens with a header row (trigger, frequency, accountable owner, exit gate), followed by its ordered runbook steps. Filter on column A to jump to a play.
A4: Play / Step | B4: Step owner (role) | C4: Action / procedure | D4: Trigger / cadence | E4: Evidence / output | F4: Controls satisfied (ISO | NIST | MAS | MGF)
A5: PLAY 1 — AI Use-Case Intake & Triage | B5: Trigger: New AI/ML/GenAI use-case proposed, or material change to an existing one | Frequency: On event | Owner — A: AI Risk Committee | R: Model Owner | Exit gate: Use-case registered & risk-tiered; documented go/no-go to proceed | F5: ISO A.4.2, A.5.2 | NIST GOVERN 1.6, MAP 1.1 | MAS M2.1, M2.2, M2.3 | MGF D1.1, D1.2, D1.6
A6: Step 1 | B6: Business / Model Owner | C6: Submit AI use-case intake form: purpose, data used, users, decisions affected, expected benefits. | D6: On event | E6: Intake form
A7: Step 2 | B7: AI Risk (2nd line) | C7: Register the use-case in the central AI inventory with dependencies and ownership. | E7: AI inventory entry
A8: Step 3 | B8: AI Risk (2nd line) | C8: Run initial risk-materiality triage scoring impact x complexity x reliance. | E8: Materiality score & rationale
A9: Step 4 | B9: AI Risk Committee | C9: Route by materiality: low -> streamlined path; high -> full impact assessment + committee review. | E9: Routing decision
A10: PLAY 2 — AI Impact & Risk Assessment | B10: Trigger: High-materiality use-case routed from intake | Frequency: On event | Owner — A: AI Risk Committee | R: AI Risk (2nd line) | Exit gate: Approved impact assessment with mitigations & documented residual risk | F10: ISO A.5.2-A.5.5 | NIST MAP 5.1, 5.2, MEASURE 1.1 | MAS M2.3, M2.4, M3.2 | MGF D1.1, D1.5 | FEAT F1-F4 (assess)
A11: Step 1 | B11: Model Owner + AI Risk | C11: Identify affected individuals/groups and analyse impact (fairness). Trigger the FEAT assessment per the FEAT Assessment Methodology (Veritas): Ethics & Accountability (F2/F3) set at org level, Fairness (F1) and Transparency (F4) run concurrently for the use case. For high-materiality use cases, initiate independent validation. | D11: On event | E11: Impact analysis
A12: Step 2 | B12: DPO | C12: Complete privacy impact assessment (DPIA) where personal data is involved. | E12: DPIA
A13: Step 3 | B13: Model Owner | C13: Document foreseeable misuse, predictable failure modes and proposed mitigations. | E13: Failure-mode register
A14: Step 4 | B14: AI Risk | C14: Assess societal/environmental impact for material or public-facing systems. | E14: Societal-impact note
A15: Step 5 | B15: AI Risk Committee | C15: Review and sign off the impact assessment; record residual risk. | E15: Signed impact assessment
A16: PLAY 3 — Development & Validation Gate | B16: Trigger: Model development complete; pre-deployment | Frequency: On event | Owner — A: AI Risk Committee | R: Independent Validation | Exit gate: Independent validation sign-off; validation report filed | F16: ISO A.6.2.2-A.6.2.4, A.7.2-A.7.6 | NIST MEASURE 2.1-2.13 | MAS M3.1, M3.3, M3.5, M3.6, M3.7, M3.8 | MGF D1.3, D1.4, D3.1-D3.9 | FEAT F1, F4
A17: Step 1 | B17: Data Owner | C17: Sign off data quality, representativeness, lineage and provenance for training/test data. | D17: On event | E17: Data sign-off
A18: Step 2 | B18: Model Developer | C18: Document model & feature selection, design decisions and requirements traceability. | E18: Model documentation
A19: Step 3 | B19: Model Developer | C19: Run testing & evaluation: performance, robustness, fairness/bias, security, explainability. | E19: Test results
A20: Step 4 | B20: Independent Validation | C20: Independently validate the model (independent of developers); issue validation opinion. | E20: Validation report
A21: PLAY 4 — Pre-Deployment Approval (Release Gate) | B21: Trigger: Validation passed; ready to deploy | Frequency: On event | Owner — A: AI Risk Committee (high-materiality) / Model Owner (low) | Exit gate: Documented deployment approval & explicit risk acceptance | F21: ISO A.6.2.5, A.9.2-A.9.4 | NIST MANAGE 1.1, MEASURE 2.3 | MAS M3.4, M3.9 | MGF D2.3, D2.4, D3.10 | FEAT F1-F4 (sign-off)
A22: Step 1 | B22: Model Owner | C22: Confirm release criteria are met and deployment environment is ready, including FEAT sign-off (F1-F4) and — for high-materiality models — independent validation sign-off per the FEAT Assessment Methodology §D. No high-materiality model is released without it. | D22: On event | E22: Release checklist
A23: Step 2 | B23: Model Owner + InfoSec | C23: Confirm human-oversight design and rollback / kill-switch plan are in place. | E23: Oversight & rollback plan
A24: Step 3 | B24: AI Risk Committee / Model Owner | C24: Accountable owner accepts residual risk; committee approves for high-materiality. | E24: Signed deployment approval
A25: PLAY 5 — Post-Deployment Monitoring | B25: Trigger: System is live | Frequency: Continuous; reviewed monthly/quarterly | Owner — A: Model Owner | R: AI Risk (2nd line) | Exit gate: Monitoring report each cycle; triggers for re-validation or retirement | F25: ISO A.6.2.6 | NIST MEASURE 2.4, 3.1, MANAGE 4.1 | MAS M3.8, M3.10 | MGF D2.5, D2.6, D3.11-D3.14, D3.16 | FEAT F1, F4 (drift)
A26: Step 1 | B26: Model Owner | C26: Monitor performance & drift against thresholds; investigate threshold breaches. | D26: Continuous; reviewed monthly/quarterly | E26: Monitoring dashboard
A27: Step 2 | B27: AI Risk | C27: Re-check fairness/bias and confirm usage stays within intended use. | E27: Periodic re-check note
A28: Step 3 | B28: AI Risk Committee | C28: Review monitoring dashboard; decide on re-validation, change or retirement. | E28: Committee minutes
A29: PLAY 6 — AI Incident Response (Runbook) | B29: Trigger: AI incident: harmful/erroneous output, drift breach, bias complaint, jailbreak/security event, agent acting out of scope | Frequency: On event | Owner — A: AI Risk Committee | R: Model Owner + InfoSec | Exit gate: Incident closed; root-cause documented; lessons fed back into controls | F29: ISO A.3.3, A.8.4, A.6.2.6 | NIST GOVERN 4.3, MANAGE 2.3, 2.4, 4.3, MEASURE 3.3 | MAS M3.11 | MGF D3.15, D3.16
A30: Step 1 | B30: Whoever detects | C30: Detect and log the incident; record time, system, symptoms, initial impact. | D30: On event | E30: Incident ticket
A31: Step 2 | B31: AI Risk + Model Owner | C31: Triage severity and classify; convene responders. | E31: Severity classification
A32: Step 3 | B32: Model Owner + InfoSec | C32: Contain: disengage / rollback / activate kill-switch; isolate affected components. | E32: Containment record
A33: Step 4 | B33: Compliance & Legal | C33: Assess against the FSM-N05 (TRM) “relevant incident” threshold — severe/widespread operational impact, or material customer-service impact. If met: notify MAS within 1 HOUR of discovery (BCM hotline) and submit root-cause & impact report within 14 DAYS. Notify internal stakeholders in parallel. | E33: MAS notification (≤1 hr); RCA & impact report (≤14 days); stakeholder notification log
A34: Step 5 | B34: Model Developer + AI Risk | C34: Root-cause analysis; remediate; verify fix. | E34: RCA & remediation
A35: Step 6 | B35: AI Risk Committee | C35: Post-incident review; update controls, tests and playbook. | E35: Post-incident review
A36: PLAY 7 — Third-Party / Foundation-Model Onboarding | B36: Trigger: Procuring external AI model/service/data, or a vendor model version change | Frequency: On event | Owner — A: AI Risk Committee | R: Model Owner + Procurement | Exit gate: Approved vendor with documented responsibility allocation & monitoring plan | F36: ISO A.10.2-A.10.4 | NIST GOVERN 6.1, 6.2, MAP 4.1, MANAGE 3.1, 3.2 | MAS M3.14 | MGF D1.5, D1.6
A37: Step 1 | B37: Model Owner + InfoSec | C37: Due diligence: responsible-AI posture, security, data rights, IP, known limitations. | D37: On event | E37: Due-diligence record
A38: Step 2 | B38: Compliance & Legal | C38: Contractual clauses: responsibility allocation, change notification, audit rights, exit. | E38: Signed contract terms
A39: Step 3 | B39: AI Risk | C39: Assess concentration risk; pin model version; define change-notification triggers. | E39: Concentration & versioning note
A40: Step 4 | B40: Model Owner | C40: Set up ongoing monitoring of the third-party model/service. | E40: Vendor monitoring plan
A41: PLAY 8 — Periodic Review & Re-Validation | B41: Trigger: Scheduled (risk-tiered cadence) or material change | Frequency: Annual / risk-tiered | Owner — A: AI Risk Committee | R: Independent Validation | Exit gate: Re-approved, or escalated for change / retirement | F41: ISO A.2.4, A.6.2.4 | NIST MEASURE 1.2, MANAGE 4.2 | MAS M2.3, M3.12 | MGF D1.2, D2.2 | FEAT F1-F4 (re-assess)
A42: Step 1 | B42: AI Risk | C42: Re-run materiality assessment; confirm risk tier still correct. | D42: Annual / risk-tiered | E42: Updated materiality
A43: Step 2 | B43: Independent Validation | C43: Re-validate model; review monitoring history and drift since last review; re-run the FEAT assessment (fairness drift F1, transparency F4) per cadence — annual for high-materiality, plus event-driven. | E43: Re-validation report
A44: Step 3 | B44: Model Owner | C44: Refresh impact assessment for any context/regulatory changes. | E44: Updated impact assessment
A45: Step 4 | B45: AI Risk Committee | C45: Decide: re-approve, require changes, or retire. | E45: Committee decision
A46: PLAY 9 — Decommissioning | B46: Trigger: Model retired or replaced | Frequency: On event | Owner — A: Model Owner | R: AI Risk (2nd line) | Exit gate: Decommissioned safely; inventory updated; records archived | F46: ISO A.6.2.6 | NIST GOVERN 1.7, MANAGE 2.4 | MAS M3.13 | MGF D1.5
A47: Step 1 | B47: Model Owner | C47: Assess impact on dependent systems/users; plan safe phase-out. | D47: On event | E47: Phase-out plan
A48: Step 2 | B48: Data Owner + DPO | C48: Handle data retention/disposal per policy and privacy obligations. | E48: Data disposal record
A49: Step 3 | B49: InfoSec | C49: Remove access and credentials; decommission infrastructure. | E49: Access-removal log
A50: Step 4 | B50: AI Risk | C50: Archive documentation & event logs; update the AI inventory. | E50: Archive & inventory update
A51: PLAY 10 — Stress-Test / Red-Team Cycle | B51: Trigger: Scheduled per hotspot cadence + before any major release | Frequency: Quarterly + pre-release | Owner — A: AI Risk Committee | R: InfoSec + AI Risk | Exit gate: Results logged in Stress-Test Tracker; remediation tracked to closure | F51: NIST MEASURE 2.6, 2.7, MANAGE 1.1-1.4 | MAS M3.6, M3.15 | see Stress-Test Tracker tab | MGF D3.8, D3.9, D4.5
A52: Step 1 | B52: AI Risk | C52: Select hotspots in scope for this cycle (see Stress-Test Tracker). | D52: Quarterly + pre-release | E52: Scope note
A53: Step 2 | B53: InfoSec | C53: Design scenario / adversarial / red-team tests; chain hotspots where useful. | E53: Test plan
A54: Step 3 | B54: InfoSec + Model Owner | C54: Execute tests in a controlled environment; capture findings. | E54: Test evidence
A55: Step 4 | B55: AI Risk | C55: Rate results and residual risk; log in tracker; raise remediation items. | E55: Updated tracker
A56: Step 5 | B56: AI Risk Committee | C56: Review results; approve residual risk or require remediation. | E56: Committee sign-off
A57: PLAY 11 — Agentic Operation & Human Oversight | B57: Trigger: Agentic AI system in live operation | Frequency: Continuous + monthly | Owner — A: AI Risk Committee | R: Model Owner + AI Risk | Exit gate: Oversight effectiveness evidenced; end-user disclosures & training current | F57: ISO A.8.2-A.8.5, A.9.3-A.9.4, A.4.6 | NIST GOVERN 5.1, MEASURE 3.3 | MAS M1.5, M3.10 | MGF D2.5, D2.6, D2.7, D4.1-D4.5
A58: Step 1 | B58: Model Owner + Compliance | C58: Publish end-user disclosures: agent capabilities, data access, limitations, and a human point of contact. | D58: Continuous | E58: Disclosure notice
A59: Step 2 | B59: Model Owner + HR (capability) | C59: Train integrating users on oversight best practice, common failure modes and tradecraft preservation. | D59: On onboarding + periodic | E59: Training records
A60: Step 3 | B60: AI Risk (2nd line) | C60: Monitor human-oversight effectiveness — override rates and approval response times — to detect automation bias. | D60: Monthly | E60: Oversight-metrics report
A61: Step 4 | B61: InfoSec + AI Risk | C61: In sensitive contexts, run end-user / red-team review of agent approval prompts and actions. | D61: Quarterly | E61: Red-team review note
A62: Step 5 | B62: AI Risk Committee | C62: Review oversight metrics and disclosures; confirm continued meaningful human accountability or require change. | D62: Quarterly | E62: Committee minutes
A65: Note:
A66: * Play 2 (AI Impact & Risk Assessment) -- trigers the FEAT assessment; Ethics/Accountability set at org level, Fairness/Transparency run per use case.
A67: * Play 3 & 4 (Validation Gate/ Release Gate) - FEAT sign-off F1-F4; no high-materiality model releases without section D validation.
A68: * Play 5 & 8 (Monitoring/ Re-validation) - fairness-drift (F1) and transparency (F4) re-assessment on cadence.

Sheet Control Library - ISO 42001
A1: Control Library - ISO 42001 — Control Tracker
A3: Control Objective | B3: Control ID | C3: Control Title | D3: Requirement (summary) | E3: Owner (role) | F3: Status | G3: Maturity (1-5) | H3: Evidence / artifact | I3: Last reviewed | J3: Next review | K3: Gap / notes | L3: Linked play | M3: Test of Design | N3: Test of Operating Effectiveness
A4: A.2 Policies related to AI | B4: A.2.2 | C4: AI policy | D4: Maintain a written, management-approved AI policy that sets out how the organisation develops and uses AI. The foundation every other control hangs off. | E4: AI Risk Cttee / Compliance | F4: Not started
A5: A.2 Policies related to AI | B5: A.2.3 | C5: Alignment with other organisational policies | D5: Ensure the AI policy is consistent with existing security, privacy, risk, HR, procurement and ethics policies; update those policies where they intersect rather than creating conflicts. | E5: AI Risk Cttee / Compliance | F5: Not started
A6: A.2 Policies related to AI | B6: A.2.4 | C6: Review of the AI policy | D6: Review the AI policy on a planned cycle and whenever something material changes (new regulation, new use case, incident lessons) to confirm continued fitness and management support. | E6: AI Risk Cttee / Compliance | F6: Not started | L6: Play 8
A7: A.3 Internal organisation | B7: A.3.2 | C7: AI roles and responsibilities | D7: Define and explicitly assign accountability and responsibility for AI activities across the life cycle (risk, impact assessment, development, oversight, data quality, security, supplier management) so nothing falls in a gap. | E7: AI Risk (2nd line) | F7: Not started
A8: A.3 Internal organisation | B8: A.3.3 | C8: Reporting of concerns | D8: Provide a reporting channel (anonymous/confidential where appropriate, protected from reprisal) for staff, contractors and external parties to raise concerns about AI, with defined investigation and escalation. | E8: AI Risk (2nd line) | F8: Not started | L8: Play 6
A9: A.4 Resources for AI systems | B9: A.4.2 | C9: Resource documentation | D9: Build and maintain an inventory of the resources AI systems rely on at each life cycle stage; resource visibility makes risk assessment, impact assessment and incident response possible. | E9: Model Owner (1st line) | F9: Not started | L9: Play 1
A10: A.4 Resources for AI systems | B10: A.4.3 | C10: Data resources | D10: Record details of every dataset used: provenance, last-updated timestamps, category (training/validation/test/production), labelling process, intended purpose, quality, retention and known bias issues. | E10: Model Owner (1st line) | F10: Not started
A11: A.4 Resources for AI systems | B11: A.4.4 | C11: Tooling resources | D11: Record the algorithms, ML models, frameworks, libraries, optimisation/evaluation methods and provisioning tools the AI system depends on, to enable reproducibility and supply-chain risk assessment. | E11: Model Owner (1st line) | F11: Not started
A12: A.4 Resources for AI systems | B12: A.4.5 | C12: System and computing resources | D12: Record the compute, storage, network and hosting environments (on-prem, cloud, edge) the system runs on, including capacity constraints, dependencies and environmental impact of the hardware. | E12: Model Owner (1st line) | F12: Not started
A13: A.4 Resources for AI systems | B13: A.4.6 | C13: Human resources | D13: Record the people and competencies involved across every phase: not just developers but operators, domain experts, testers, oversight roles, and change/handover/decommissioning roles. | E13: Model Owner (1st line) | F13: Not started | L13: Play 11
A14: A.5 Assessing impacts of AI systems | B14: A.5.2 | C14: AI system impact assessment process | D14: Stand up a repeatable process for assessing how an AI system could affect people and society: triggers (criticality, complexity, sensitivity), scope, who performs it, and how outputs feed design/deployment/review. | E14: AI Risk (2nd line) | F14: Not started | L14: Play 1, 2
A15: A.5 Assessing impacts of AI systems | B15: A.5.3 | C15: Documentation of AI system impact assessments | D15: Keep written records of every impact assessment (intended use, foreseeable misuse, predictable failures and mitigations, affected groups, oversight arrangements) and retain them for a defined period. | E15: AI Risk (2nd line) | F15: Not started | L15: Play 2
A16: A.5 Assessing impacts of AI systems | B16: A.5.4 | C16: Assessing AI system impact on individuals or groups of individuals | D16: Consider how the system could affect individuals or groups: fairness, accountability, transparency, privacy, safety, health, accessibility, financial and human-rights consequences, with attention to protected groups. | E16: AI Risk (2nd line) | F16: Not started | L16: Play 2
A17: A.5 Assessing impacts of AI systems | B17: A.5.5 | C17: Assessing societal impacts of AI systems | D17: Extend the assessment beyond direct users: environmental footprint, economic impact, effects on democratic/government processes, public health and safety, cultural/ethical norms and potential for deliberate misuse. | E17: AI Risk (2nd line) | F17: Not started | L17: Play 2
A18: A.6 AI system life cycle | B18: A.6.1.2 | C18: Objectives for responsible development of AI system | D18: Set clear responsible-development objectives (fairness, transparency, robustness, privacy, safety) and bake them into development as measurable design inputs teams are accountable to. | E18: Model Developer / Indep. Validation | F18: Not started
A19: A.6 AI system life cycle | B19: A.6.1.3 | C19: Processes for responsible design and development of AI systems | D19: Document the actual steps for responsible design/build: life cycle stages, testing requirements, human oversight, training-data rules, release criteria, approvals, change control and stakeholder engagement. | E19: Model Developer / Indep. Validation | F19: Not started
A20: A.6 AI system life cycle | B20: A.6.2.2 | C20: AI system requirements and specification | D20: Capture functional and non-functional requirements (including risk and responsible-AI requirements) before building, document rationale, and keep requirements under change control as the system evolves. | E20: Model Developer / Indep. Validation | F20: Not started | L20: Play 3
A21: A.6 AI system life cycle | B21: A.6.2.3 | C21: Documentation of AI system design and development | D21: Maintain a traceable record of design decisions (ML approach, algorithms, data assumptions, components, security threats, UI, human interaction, interoperability) tied back to requirements. | E21: Model Developer / Indep. Validation | F21: Not started | L21: Play 3
A22: A.6 AI system life cycle | B22: A.6.2.4 | C22: AI system verification and validation | D22: Define how the system is verified (built right) and validated (built the right thing): testing methodologies, test-data selection, release-criteria thresholds and acceptable error rates for the use case. | E22: Model Developer / Indep. Validation | F22: Not started | L22: Play 3, 8
A23: A.6 AI system life cycle | B23: A.6.2.5 | C23: AI system deployment | D23: Maintain a written deployment plan with release criteria, approvals and rollback; do not release until satisfied, especially when the deployment environment differs from development. | E23: Model Developer / Indep. Validation | F23: Not started | L23: Play 4
A24: A.6 AI system life cycle | B24: A.6.2.6 | C24: AI system operation and monitoring | D24: Define day-to-day running: performance monitoring (incl. drift, continuous-learning changes, AI-specific threats like data poisoning), repairs, updates and user support, each with clear ownership. | E24: Model Developer / Indep. Validation | F24: Not started | L24: Play 5, 6, 9
A25: A.6 AI system life cycle | B25: A.6.2.7 | C25: AI system technical documentation | D25: Decide what technical documentation each audience (users, partners, auditors, regulators) needs and deliver it usably: intended purpose, usage instructions, run-time assumptions, limitations, monitoring functions. | E25: Model Developer / Indep. Validation | F25: Not started
A26: A.6 AI system life cycle | B26: A.6.2.8 | C26: AI system recording of event logs | D26: Decide what events get logged and at which stages (at minimum during operation) to evidence behaviour, trace issues, support audit/incident response and detect drift outside intended conditions. | E26: Model Developer / Indep. Validation | F26: Not started
A27: A.7 Data for AI systems | B27: A.7.2 | C27: Data for development and enhancement of AI system | D27: Operate data-management processes for development data: privacy and security, representativeness against the operational domain, explainability/provenance, and accuracy/integrity of underlying data. | E27: Data Owner / Steward | F27: Not started | L27: Play 3
A28: A.7 Data for AI systems | B28: A.7.3 | C28: Acquisition of data | D28: Document where each dataset comes from and how it was chosen (internal/purchased/shared/open/synthetic, static/streamed), known biases, data rights, prior uses and metadata, so downstream decisions are defensible. | E28: Data Owner / Steward | F28: Not started | L28: Play 3
A29: A.7 Data for AI systems | B29: A.7.4 | C29: Quality of data for AI systems | D29: Set explicit data-quality criteria (accuracy, completeness, currency, representativeness), verify training and production data meet them, and address fairness/bias impact, adjusting data or model as needed. | E29: Data Owner / Steward | F29: Not started | L29: Play 3
A30: A.7 Data for AI systems | B30: A.7.5 | C30: Data provenance | D30: Track where each dataset came from and what happened to it (creation, updates, transformations, validation, transfers, sharing) across the data and system life cycles so lineage stays recoverable. | E30: Data Owner / Steward | F30: Not started | L30: Play 3
A31: A.7 Data for AI systems | B31: A.7.6 | C31: Data preparation | D31: Decide which data-preparation techniques (cleaning, labelling, augmentation, normalisation, encoding) are acceptable, document the methods chosen per dataset and record the rationale so choices can be reviewed/repeated. | E31: Data Owner / Steward | F31: Not started | L31: Play 3
A32: A.8 Information for interested parties | B32: A.8.2 | C32: System documentation and information for users | D32: Give users enough information to operate the system safely and responsibly: capabilities, limits, expected inputs/outputs, known failure modes and human-oversight options, in plain language. | E32: Compliance & Legal | F32: Not started | L32: Play 11
A33: A.8 Information for interested parties | B33: A.8.3 | C33: External reporting | D33: Provide a way for anyone affected (customers, data subjects, public) to report problems, complaints or unintended consequences, and define how reports are triaged, investigated and resolved. | E33: Compliance & Legal | F33: Not started | L33: Play 11
A34: A.8 Information for interested parties | B34: A.8.4 | C34: Communication of incidents | D34: Plan in advance how to inform users and affected parties when an AI incident occurs: what to say, who says it, how fast and through what channel, aligned with regulatory notification obligations. | E34: Compliance & Legal | F34: Not started | L34: Play 6, 11
A35: A.8 Information for interested parties | B35: A.8.5 | C35: Information for interested parties | D35: Decide what other AI-system information (beyond incidents) must be proactively shared with regulators, partners, customers and the public, and document how, when and in what form. | E35: Compliance & Legal | F35: Not started | L35: Play 11
A36: A.9 Use of AI systems | B36: A.9.2 | C36: Processes for responsible use of AI systems | D36: Document how the system is meant to be used responsibly: human-oversight expectations, acceptable-use rules, escalation paths, operator training and conditions under which use is paused or stopped. | E36: Model Owner (1st line) | F36: Not started | L36: Play 4
A37: A.9 Use of AI systems | B37: A.9.3 | C37: Objectives for responsible use of AI system | D37: Define responsible-use objectives the system is operated against (fairness thresholds, human-in-the-loop requirements, safety tolerances) so operational decisions have a clear reference. | E37: Model Owner (1st line) | F37: Not started | L37: Play 4, 11
A38: A.9 Use of AI systems | B38: A.9.4 | C38: Intended use of the AI system | D38: Prevent scope creep: ensure the system is used for its designed purpose, with controls that stop it being repurposed, extended or used in unintended contexts without re-assessment. | E38: Model Owner (1st line) | F38: Not started | L38: Play 4, 11
... A41: A.10 Third-party and customer relationships | B41: A.10.4 | C41: Customers | D41: Factor customer obligations (contracts, regulatory promises, duty of care, trust commitments) into the responsible-AI approach before decisions about development, provision or use are finalised. | E41: Procurement + AI Risk | F41: Not started | L41: Play 7

Sheet Control Library - NIST AI RMF
A1: Control Library - NIST AI RMF — Control Tracker
A3: Function | B3: Category | C3: Category statement | D3: Subcategory | E3: Subcategory outcome | F3: Owner (role) | G3: Status | H3: Maturity (1-5) | I3: Evidence / artifact | J3: Last reviewed | K3: Next review | L3: Gap / notes | M3: Linked play | N3: Test of Design | O3: Test of Operating Effectiveness
A4: GOVERN | B4: GOVERN 1 | C4: Policies, processes, procedures and practices across the organization related to the mapping, measuring and managing of AI risks are in place, transparent, and implemented effectively. | D4: GOVERN 1.1 | E4: Legal and regulatory requirements involving AI are understood, managed, and documented. | F4: AI Risk Cttee / Senior Mgmt | G4: Not started
A5: GOVERN | B5: GOVERN 1 | D5: GOVERN 1.2 | E5: The characteristics of trustworthy AI are integrated into organizational policies, processes, procedures, and practices. | F5: AI Risk Cttee / Senior Mgmt | G5: Not started
A6: GOVERN | B6: GOVERN 1 | D6: GOVERN 1.3 | E6: Processes, procedures and practices are in place to determine the needed level of risk management activities based on the organization's risk tolerance. | F6: AI Risk Cttee / Senior Mgmt | G6: Not started
A7: GOVERN | B7: GOVERN 1 | D7: GOVERN 1.4 | E7: The risk management process and its outcomes are established through transparent policies, procedures and other controls based on organizational risk priorities. | F7: AI Risk Cttee / Senior Mgmt | G7: Not started
A8: GOVERN | B8: GOVERN 1 | D8: GOVERN 1.5 | E8: Ongoing monitoring and periodic review of the risk management process and its outcomes are planned, and organizational roles and responsibilities are clearly defined, including determining the frequency of periodic review. | F8: AI Risk Cttee / Senior Mgmt | G8: Not started
A9: GOVERN | B9: GOVERN 1 | D9: GOVERN 1.6 | E9: Mechanisms are in place to inventory AI systems and are resourced according to organizational risk priorities. | F9: AI Risk Cttee / Senior Mgmt | G9: Not started | M9: Play 1
A10: GOVERN | B10: GOVERN 1 | D10: GOVERN 1.7 | E10: Processes and procedures are in place for decommissioning and phasing out AI systems safely and in a manner that does not increase risks or decrease the organization's trustworthiness. | F10: AI Risk Cttee / Senior Mgmt | G10: Not started | M10: Play 9
A11: GOVERN | B11: GOVERN 2 | C11: Accountability structures are in place so that the appropriate teams and individuals are empowered, responsible, and trained for mapping, measuring and managing AI risks. | D11: GOVERN 2.1 | E11: Roles and responsibilities and lines of communication related to mapping, measuring and managing AI risks are documented and are clear to individuals and teams throughout the organization. | F11: AI Risk Cttee / Senior Mgmt | G11: Not started
A12: GOVERN | B12: GOVERN 2 | D12: GOVERN 2.2 | E12: The organization's personnel and partners receive AI risk management training to enable them to perform their duties and responsibilities consistent with related policies, procedures and agreements. | F12: AI Risk Cttee / Senior Mgmt | G12: Not started
A13: GOVERN | B13: GOVERN 2 | D13: GOVERN 2.3 | E13: Executive leadership of the organization takes responsibility for decisions about risks associated with AI system development and deployment. | F13: AI Risk Cttee / Senior Mgmt | G13: Not started
A14: GOVERN | B14: GOVERN 3 | C14: Workforce diversity, equity, inclusion and accessibility processes are prioritized in the mapping, measuring and managing of AI risks throughout the lifecycle. | D14: GOVERN 3.1 | E14: Decision-making related to mapping, measuring and managing AI risks throughout the lifecycle is informed by a diverse team (e.g., diversity of demographics, disciplines, experience, expertise, and backgrounds). | F14: AI Risk Cttee / Senior Mgmt | G14: Not started
A15: GOVERN | B15: GOVERN 3 | D15: GOVERN 3.2 | E15: Policies and procedures are in place to define and differentiate roles and responsibilities for human-AI configurations and oversight of AI systems. | F15: AI Risk Cttee / Senior Mgmt | G15: Not started
A16: GOVERN | B16: GOVERN 4 | C16: Organizational teams are committed to a culture that considers and communicates AI risk. | D16: GOVERN 4.1 | E16: Organizational policies and practices are in place to foster a critical thinking and safety-first mindset in the design, development, deployment, and uses of AI systems to minimize potential negative impacts. | F16: AI Risk Cttee / Senior Mgmt | G16: Not started
A17: GOVERN | B17: GOVERN 4 | D17: GOVERN 4.2 | E17: Organizational teams document the risks and potential impacts of the AI technology they design, develop, deploy, evaluate and use, and they communicate about the impacts more broadly. | F17: AI Risk Cttee / Senior Mgmt | G17: Not started
A18: GOVERN | B18: GOVERN 4 | D18: GOVERN 4.3 | E18: Organizational practices are in place to enable AI testing, identification of incidents, and information sharing. | F18: AI Risk Cttee / Senior Mgmt | G18: Not started | M18: Play 6
A19: GOVERN | B19: GOVERN 5 | C19: Processes are in place for robust engagement with relevant AI actors. | D19: GOVERN 5.1 | E19: Organizational policies and practices are in place to collect, consider, prioritize and integrate feedback from those external to the team that developed or deployed the AI system regarding the potential individual and societal impacts related to AI risks. | F19: AI Risk Cttee / Senior Mgmt | G19: Not started | M19: Play 11
A20: GOVERN | B20: GOVERN 5 | D20: GOVERN 5.2 | E20: Mechanisms are established to enable the team that developed or deployed AI systems to regularly incorporate adjudicated feedback from relevant AI actors into system design and implementation. | F20: AI Risk Cttee / Senior Mgmt | G20: Not started
A21: GOVERN | B21: GOVERN 6 | C21: Policies and procedures are in place to address AI risks and benefits arising from third-party software and data and other supply chain issues. | D21: GOVERN 6.1 | E21: Policies and procedures are in place that address AI risks associated with third-party entities, including risks of infringement of a third party's intellectual property or other rights. | F21: AI Risk Cttee / Senior Mgmt | G21: Not started | M21: Play 7
A22: GOVERN | B22: GOVERN 6 | D22: GOVERN 6.2 | E22: Contingency processes are in place to handle failures or incidents in third-party data or AI systems deemed to be high-risk. | F22: AI Risk Cttee / Senior Mgmt | G22: Not started | M22: Play 7
A23: MAP | B23: MAP 1 | C23: Context is established and understood. | D23: MAP 1.1 | E23: Intended purposes, potentially beneficial uses, context-specific laws, norms and expectations, and prospective settings in which the AI system will be deployed are understood and documented. | F23: Model Owner + AI Risk | G23: Not started | M23: Play 1
A24: MAP | B24: MAP 1 | D24: MAP 1.2 | E24: Interdisciplinary AI actors, competencies, skills and capacities for establishing context reflect demographic diversity and broad domain and user experience expertise, and their participation is documented. Opportunities for interdisciplinary collaboration are prioritized. | F24: Model Owner + AI Risk | G24: Not started
A25: MAP | B25: MAP 1 | D25: MAP 1.3 | E25: The organization's mission and relevant goals for AI technology are understood and documented. | F25: Model Owner + AI Risk | G25: Not started
A26: MAP | B26: MAP 1 | D26: MAP 1.4 | E26: The business value or context of business use has been clearly defined or, in the case of assessing existing AI systems, re-evaluated. | F26: Model Owner + AI Risk | G26: Not started
A27: MAP | B27: MAP 1 | D27: MAP 1.5 | E27: Organizational risk tolerances are determined and documented. | F27: Model Owner + AI Risk | G27: Not started
A28: MAP | B28: MAP 1 | D28: MAP 1.6 | E28: System requirements (e.g., the system shall respect the privacy of its users) are elicited from and understood by relevant AI actors. Design decisions take socio-technical implications into account to address AI risks. | F28: Model Owner + AI Risk | G28: Not started
A29: MAP | B29: MAP 2 | C29: Categorization of the AI system is performed. | D29: MAP 2.1 | E29: The specific tasks and methods used to implement the tasks that the AI system will support are defined (e.g., classifiers, generative models, recommenders). | F29: Model Owner + AI Risk | G29: Not started
A30: MAP | B30: MAP 2 | D30: MAP 2.2 | E30: Information about the AI system's knowledge limits and how system output may be utilized and overseen by humans is documented. | F30: Model Owner + AI Risk | G30: Not started
A31: MAP | B31: MAP 2 | D31: MAP 2.3 | E31: Scientific integrity and TEVV considerations are identified and documented, including those related to experimental design, data collection and selection (e.g., availability, representativeness, suitability), system trustworthiness, and construct validation. | F31: Model Owner + AI Risk | G31: Not started
A32: MAP | B32: MAP 3 | C32: AI capabilities, targeted usage, goals, and expected benefits and costs compared with appropriate benchmarks are understood. | D32: MAP 3.1 | E32: Potential benefits of intended AI system functionality and performance are examined and documented. | F32: Model Owner + AI Risk | G32: Not started
A33: MAP | B33: MAP 3 | D33: MAP 3.2 | E33: Potential costs, including non-monetary costs, which result from expected or realized AI errors or system functionality and trustworthiness, as connected to organizational risk tolerance, are examined and documented. | F33: Model Owner + AI Risk | G33: Not started
A34: MAP | B34: MAP 3 | D34: MAP 3.3 | E34: Targeted application scope is specified and documented based on the system's capability, established context, and AI system categorization. | F34: Model Owner + AI Risk | G34: Not started
A35: MAP | B35: MAP 3 | D35: MAP 3.4 | E35: Processes for operator and practitioner proficiency with AI system performance and trustworthiness, and relevant technical standards and certifications, are defined, assessed and documented. | F35: Model Owner + AI Risk | G35: Not started
A36: MAP | B36: MAP 3 | D36: MAP 3.5 | E36: Processes for human oversight are defined, assessed and documented in accordance with organizational policies from the GOVERN function. | F36: Model Owner + AI Risk | G36: Not started
A37: MAP | B37: MAP 4 | C37: Risks and benefits are mapped for all components of the AI system including third-party software and data. | D37: MAP 4.1 | E37: Approaches for mapping AI technology and legal risks of its components, including the use of third-party data or software, are in place, followed and documented, as are risks of infringement of a third party's intellectual property or other rights. | F37: Model Owner + AI Risk | G37: Not started | M37: Play 7
A38: MAP | B38: MAP 4 | D38: MAP 4.2 | E38: Internal risk controls for components of the AI system, including third-party AI technologies, are identified and documented. | F38: Model Owner + AI Risk | G38: Not started
A39: MAP | B39: MAP 5 | C39: Impacts to individuals, groups, communities, organizations, and society are characterized. | D39: MAP 5.1 | E39: Likelihood and magnitude of each identified impact (both potentially beneficial and harmful) based on expected use, past uses of AI systems in similar contexts, public incident reports, feedback, or other data are identified and documented. | F39: Model Owner + AI Risk | G39: Not started | M39: Play 2
A40: MAP | B40: MAP 5 | D40: MAP 5.2 | E40: Practices and personnel for supporting regular engagement with relevant AI actors and integrating feedback about positive, negative and unanticipated impacts are in place and documented. | F40: Model Owner + AI Risk | G40: Not started | M40: Play 2
A41: MEASURE | B41: MEASURE 1 | C41: Appropriate methods and metrics are identified and applied. | D41: MEASURE 1.1 | E41: Approaches and metrics for measurement of AI risks enumerated during the MAP function are selected for implementation starting with the most significant AI risks. Risks or trustworthiness characteristics that cannot be measured are properly documented. | F41: Indep. Validation / InfoSec | G41: Not started | M41: Play 2
A42: MEASURE | B42: MEASURE 1 | D42: MEASURE 1.2 | E42: Appropriateness of AI metrics and effectiveness of existing controls are regularly assessed and updated, including reports of errors and potential impacts on affected communities. | F42: Indep. Validation / InfoSec | G42: Not started | M42: Play 8
A43: MEASURE | B43: MEASURE 1 | D43: MEASURE 1.3 | E43: Internal experts who did not serve as front-line developers for the system and/or independent assessors are involved in regular assessments and updates. Domain experts, users, AI actors external to the team, and affected communities are consulted as necessary. | F43: Indep. Validation / InfoSec | G43: Not started
A44: MEASURE | B44: MEASURE 2 | C44: AI systems are evaluated for trustworthy characteristics. | D44: MEASURE 2.1 | E44: Test sets, metrics and details about the tools used during TEVV are documented. | F44: Indep. Validation / InfoSec | G44: Not started | M44: Play 3
A45: MEASURE | B45: MEASURE 2 | D45: MEASURE 2.2 | E45: Evaluations involving human subjects meet applicable requirements (including human subject protection) and are representative of the relevant population. | F45: Indep. Validation / InfoSec | G45: Not started | M45: Play 3
A46: MEASURE | B46: MEASURE 2 | D46: MEASURE 2.3 | E46: AI system performance or assurance criteria are measured qualitatively or quantitatively and demonstrated for conditions similar to deployment setting(s). Measures are documented. | F46: Indep. Validation / InfoSec | G46: Not started | M46: Play 3, 4
A47: MEASURE | B47: MEASURE 2 | D47: MEASURE 2.4 | E47: The functionality and behavior of the AI system and its components, as identified in the MAP function, are monitored when in production. | F47: Indep. Validation / InfoSec | G47: Not started | M47: Play 3, 5
A48: MEASURE | B48: MEASURE 2 | D48: MEASURE 2.5 | E48: The AI system to be deployed is demonstrated to be valid and reliable. Limitations of the generalizability beyond the conditions under which the technology was developed are documented. | F48: Indep. Validation / InfoSec | G48: Not started | M48: Play 3
A49: MEASURE | B49: MEASURE 2 | D49: MEASURE 2.6 | E49: The AI system is evaluated regularly for safety risks. It is demonstrated to be safe, its residual negative risk does not exceed the risk tolerance, and it can fail safely, particularly if made to operate beyond its knowledge limits. | F49: Indep. Validation / InfoSec | G49: Not started | M49: Play 3, 10
A50: MEASURE | B50: MEASURE 2 | D50: MEASURE 2.7 | E50: AI system security and resilience, as identified in the MAP function, are evaluated and documented. | F50: Indep. Validation / InfoSec | G50: Not started | M50: Play 3, 10
A51: MEASURE | B51: MEASURE 2 | D51: MEASURE 2.8 | E51: Risks associated with transparency and accountability, as identified in the MAP function, are examined and documented. | F51: Indep. Validation / InfoSec | G51: Not started | M51: Play 3
A52: MEASURE | B52: MEASURE 2 | D52: MEASURE 2.9 | E52: The AI model is explained, validated and documented, and AI system output is interpreted within its context to inform responsible use and governance. | F52: Indep. Validation / InfoSec | G52: Not started | M52: Play 3
A53: MEASURE | B53: MEASURE 2 | D53: MEASURE 2.10 | E53: Privacy risk of the AI system, as identified in the MAP function, is examined and documented. | F53: Indep. Validation / InfoSec | G53: Not started | M53: Play 3
A54: MEASURE | B54: MEASURE 2 | D54: MEASURE 2.11 | E54: Fairness and bias, as identified in the MAP function, are evaluated and results are documented. | F54: Indep. Validation / InfoSec | G54: Not started | M54: Play 3
A55: MEASURE | B55: MEASURE 2 | D55: MEASURE 2.12 | E55: Environmental impact and sustainability of AI model training and management activities, as identified in the MAP function, are assessed and documented. | F55: Indep. Validation / InfoSec | G55: Not started | M55: Play 3
A56: MEASURE | B56: MEASURE 2 | D56: MEASURE 2.13 | E56: Effectiveness of the employed TEVV metrics and processes in the MEASURE function are evaluated and documented. | F56: Indep. Validation / InfoSec | G56: Not started | M56: Play 3
A57: MEASURE | B57: MEASURE 3 | C57: Mechanisms for tracking identified AI risks over time are in place. | D57: MEASURE 3.1 | E57: Approaches, personnel and documentation are in place to regularly identify and track existing, unanticipated and emergent AI risks based on factors such as intended and actual performance in deployed contexts. | F57: Indep. Validation / InfoSec | G57: Not started | M57: Play 5
A58: MEASURE | B58: MEASURE 3 | D58: MEASURE 3.2 | E58: Risk tracking approaches are considered for settings where AI risks are difficult to assess using currently available measurement techniques or where metrics are not yet available. | F58: Indep. Validation / InfoSec | G58: Not started
A59: MEASURE | B59: MEASURE 3 | D59: MEASURE 3.3 | E59: Feedback processes for end users and impacted communities to report problems and appeal system outcomes are established and integrated into AI system evaluation metrics. | F59: Indep. Validation / InfoSec | G59: Not started | M59: Play 6, 11
A60: MEASURE | B60: MEASURE 4 | C60: Feedback about efficacy of measurement is gathered and assessed. | D60: MEASURE 4.1 | E60: Measurement approaches for identifying AI risks are connected to deployment context(s) and informed through consultation with domain experts and other end users. Approaches are documented. | F60: Indep. Validation / InfoSec | G60: Not started
A61: MEASURE | B61: MEASURE 4 | D61: MEASURE 4.2 | E61: Measurement results regarding AI system trustworthiness in deployment context(s) and across the AI lifecycle are informed by input from domain experts and relevant AI actors to validate whether the system is performing consistently as intended. Results are documented. | F61: Indep. Validation / InfoSec | G61: Not started
A62: MEASURE | B62: MEASURE 4 | D62: MEASURE 4.3 | E62: Measurable performance improvements or declines based on consultations with relevant AI actors, including affected communities, and field data about context-relevant risks and trustworthiness characteristics are identified and documented. | F62: Indep. Validation / InfoSec | G62: Not started
A63: MANAGE | B63: MANAGE 1 | C63: AI risks based on assessments and other analytical output from the MAP and MEASURE functions are prioritized, responded to, and managed. | D63: MANAGE 1.1 | E63: A determination is made as to whether the AI system achieves its intended purposes and stated objectives and whether its development or deployment should proceed. | F63: Model Owner + AI Risk | G63: Not started | M63: Play 4, 10
A64: MANAGE | B64: MANAGE 1 | D64: MANAGE 1.2 | E64: Treatment of documented AI risks is prioritized based on impact, likelihood and available resources or methods. | F64: Model Owner + AI Risk | G64: Not started | M64: Play 10
A65: MANAGE | B65: MANAGE 1 | D65: MANAGE 1.3 | E65: Responses to the AI risks deemed high priority, as identified by the MAP function, are developed, planned and documented. Risk response options can include mitigating, transferring, avoiding or accepting. | F65: Model Owner + AI Risk | G65: Not started | M65: Play 10
A66: MANAGE | B66: MANAGE 1 | D66: MANAGE 1.4 | E66: Negative residual risks (defined as the sum of all unmitigated risks) to both downstream acquirers of AI systems and end users are documented. | F66: Model Owner + AI Risk | G66: Not started | M66: Play 10
A67: MANAGE | B67: MANAGE 2 | C67: Strategies to maximize AI benefits and minimize negative impacts are planned, prepared, implemented, documented, and informed by input from relevant AI actors. | D67: MANAGE 2.1 | E67: Resources required to manage AI risks are taken into account, along with viable non-AI alternative systems, approaches or methods, to reduce the magnitude or likelihood of potential impacts. | F67: Model Owner + AI Risk | G67: Not started
A68: MANAGE | B68: MANAGE 2 | D68: MANAGE 2.2 | E68: Mechanisms are in place and applied to sustain the value of deployed AI systems. | F68: Model Owner + AI Risk | G68: Not started
A69: MANAGE | B69: MANAGE 2 | D69: MANAGE 2.3 | E69: Procedures are followed to respond to and recover from a previously unknown risk when it is identified. | F69: Model Owner + AI Risk | G69: Not started | M69: Play 6
A70: MANAGE | B70: MANAGE 2 | D70: MANAGE 2.4 | E70: Mechanisms are in place and applied, and responsibilities are assigned and understood, to supersede, disengage or deactivate AI systems that demonstrate performance or outcomes inconsistent with intended use. | F70: Model Owner + AI Risk | G70: Not started | M70: Play 6, 9
A71: MANAGE | B71: MANAGE 3 | C71: AI risks and benefits from third-party entities are managed. | D71: MANAGE 3.1 | E71: AI risks and benefits from third-party resources are regularly monitored, and risk controls are applied and documented. | F71: Model Owner + AI Risk | G71: Not started | M71: Play 7
A72: MANAGE | B72: MANAGE 3 | D72: MANAGE 3.2 | E72: Pre-trained models which are used for development are monitored as part of AI system regular monitoring and maintenance. | F72: Model Owner + AI Risk | G72: Not started | M72: Play 7
A73: MANAGE | B73: MANAGE 4 | C73: Risk treatments, including response and recovery, and communication plans for the identified and measured AI risks are documented and monitored regularly. | D73: MANAGE 4.1 | E73: Post-deployment AI system monitoring plans are implemented, including mechanisms for capturing and evaluating input from users and other relevant AI actors, appeal and override, decommissioning, incident response, recovery, and change management. | F73: Model Owner + AI Risk | G73: Not started | M73: Play 5
A74: MANAGE | B74: MANAGE 4 | D74: MANAGE 4.2 | E74: Measurable activities for continual improvements are integrated into AI system updates and include regular engagement with interested parties, including relevant AI actors. | F74: Model Owner + AI Risk | G74: Not started | M74: Play 8
A75: MANAGE | B75: MANAGE 4 | D75: MANAGE 4.3 | E75: Incidents and errors are communicated to relevant AI actors, including affected communities. Processes for tracking, responding to and recovering from incidents and errors are followed and documented. | F75: Model Owner + AI Risk | G75: Not started | M75: Play 6

Sheet Control Library - MAS
A1: Control Library - MAS — Control Tracker
A3: MAS Pillar | B3: MAS ref | C3: MAS expectation area | D3: Primary MAS source | E3: ISO 42001 | F3: NIST AI RMF | G3: Owner (role) | H3: Status | I3: Maturity (1-5) | J3: Evidence / artifact | K3: Last reviewed | L3: Next review | M3: Gap / notes | N3: Linked play | O3: Linked agentic controls (MGF | SAFR) | P3: Test of Design | Q3: Test of Operating Effectiveness | R3: Linked CSA PA
A4: 1. AI Oversight & Governance | B4: M1.1 | C4: Board & senior management accountability for AI risk (risk appetite, framework approval) | D4: AIRG Consultation Paper P017-2025 (Nov 2025, proposed); AI MRM Paper (Dec 2024) | E4: A.2.2; A.3.2 | F4: GOVERN 1.1; GOVERN 2.3 | G4: AI Risk Cttee / Senior Mgmt | H4: Not started | J4: Board mandate; approved framework | O4: MGF D2.1 | SAFR S1.2 | R4: PA 2, PA 6
A5: 1. AI Oversight & Governance | B5: M1.2 | C5: AI policies & guiding principles (fair, ethical, accountable, transparent use) | D5: FEAT (2018); AIRG Consultation Paper P017-2025 (Nov 2025, proposed) | E5: A.2.2; A.2.3; A.2.4 | F5: GOVERN 1.2; GOVERN 1.4; GOVERN 4.1 | G5: AI Risk Cttee / Senior Mgmt | H5: Not started | J5: AI use policy | M5: carry the FEAT/fairness control mappings that feed those principles. | R5: PA 2
A6: 1. AI Oversight & Governance | B6: M1.3 | C6: Cross-functional AI oversight forum / AI risk committee | D6: AI MRM Paper (Dec 2024); AIRG Consultation Paper P017-2025 (Nov 2025, proposed) | E6: A.3.2 | F6: GOVERN 2.1; GOVERN 4.3 | G6: AI Risk Cttee / Senior Mgmt | H6: Not started | J6: Committee terms of reference; minutes | R6: PA 4
A7: 1. AI Oversight & Governance | B7: M1.4 | C7: AI risk appetite & risk tolerance setting | D7: AIRG Consultation Paper P017-2025 (Nov 2025, proposed) | E7: A.5.2 | F7: GOVERN 1.3; MAP 1.5 | G7: AI Risk Cttee / Senior Mgmt | H7: Not started | J7: AI risk appetite statement | R7: PA 4
A8: 1. AI Oversight & Governance | B8: M1.5 | C8: AI literacy, culture & training across the organisation | D8: AIRG Consultation Paper P017-2025 (Nov 2025, proposed); AI MRM Paper (Dec 2024) | E8: A.3.3; A.4.6 | F8: GOVERN 2.2; GOVERN 4.1 | G8: AI Risk Cttee / Senior Mgmt | H8: Not started | J8: Training plan & records | N8: Play 11 | O8: MGF D4.3, D4.4 | R8: PA 2
A9: 2. AI Risk Mgmt Systems & Processes | B9: M2.1 | C9: Consistent identification of where AI is used | D9: AI MRM Paper (Dec 2024); AIRG Consultation Paper P017-2025 (Nov 2025, proposed) | E9: A.4.2 | F9: GOVERN 1.6; MAP 1.1 | G9: AI Risk (2nd line) | H9: Not started | J9: AI identification procedure | N9: Play 1 | R9: PA 2, PA 7
A10: 2. AI Risk Mgmt Systems & Processes | B10: M2.2 | C10: AI inventory — central register of models / use-cases / dependencies | D10: AI MRM Paper (Dec 2024); AIRG Consultation Paper P017-2025 (Nov 2025, proposed) | E10: A.4.2; A.4.3; A.4.4; A.4.5 | F10: GOVERN 1.6 | G10: AI Risk (2nd line) | H10: Not evidenced | I10: 1 | J10: [sample_evidence.md] # Sample evidence pack — Meridian Capital Pte Ltd (fictional) Paste each block into the Evidence box for the named control. Expected ratings are what a careful 2LoD reviewer would give; compare against what the model proposes. --- ## 1. SAFR S1.1 — Agent identity & registration ### 1a. Policy only — expect PARTIAL Meridian AI Acceptable Use Policy v2.1, section 4.3 (approved by the AI Risk Committee, 14 March 2026): "All AI agents, including autonomous and semi-autonomo | K10: 46271 | M10: inventory record showing AGT-0142 is registered | Accepted by Unnamed reviewer | N10: Play 1 | R10: PA 2, PA 7
A11: 2. AI Risk Mgmt Systems & Processes | B11: M2.3 | C11: Risk materiality assessment (impact, complexity, reliance; inherent & residual) | D11: AI MRM Paper (Dec 2024); AIRG Consultation Paper P017-2025 (Nov 2025, proposed) | E11: A.5.2; A.5.3; A.5.4; A.5.5 | F11: MAP 2.2; MAP 3.2; MAP 5.1; MEASURE 1.1 | G11: AI Risk (2nd line) | H11: Not started | J11: Risk materiality assessment record | N11: Play 1, 2, 8 | O11: MGF D1.1, D1.2 | SAFR S1.5 | R11: PA 6
A12: 2. AI Risk Mgmt Systems & Processes | B12: M2.4 | C12: AI risk identification & assessment across the lifecycle | D12: AIRG Consultation Paper P017-2025 (Nov 2025, proposed) | E12: A.5.2; A.5.3 | F12: MAP 4.1; MAP 5.1; MANAGE 1.1; MANAGE 1.2 | G12: AI Risk (2nd line) | H12: Not started | J12: Lifecycle risk register | N12: Play 2 | R12: PA 6
A13: 3. AI Lifecycle Controls | B13: M3.1 | C13: Data management, quality, representativeness & provenance | D13: AI MRM Paper (Dec 2024); AIRG Consultation Paper P017-2025 (Nov 2025, proposed) | E13: A.7.2; A.7.3; A.7.4; A.7.5; A.7.6 | F13: MAP 2.3; MEASURE 2.1 | G13: Model Owner + InfoSec | H13: Not started | J13: Data lineage & quality records | N13: Play 3 | R13: —
A14: 3. AI Lifecycle Controls | B14: M3.2 | C14: Fairness & bias mitigation | D14: FEAT (2018); AIRG Consultation Paper P017-2025 (Nov 2025, proposed) | E14: A.5.4; A.7.4 | F14: MEASURE 2.11 | G14: Model Owner + InfoSec | H14: Not started | J14: Fairness assessment | M14: carry the FEAT/fairness control mappings that feed those principles. | N14: Play 2 | R14: —
A15: 3. AI Lifecycle Controls | B15: M3.3 | C15: Transparency & explainability of AI outputs | D15: FEAT (2018); AIRG Consultation Paper P017-2025 (Nov 2025, proposed) | E15: A.6.2.7; A.8.2 | F15: MAP 2.2; MEASURE 2.8; MEASURE 2.9 | G15: Model Owner + InfoSec | H15: Not started | J15: Model Cards; explainability notes | M15: carry the FEAT/fairness control mappings that feed those principles. | N15: Play 3 | O15: MGF D2.7, D4.1, D4.2 | SAFR S3.2 | R15: —
A16: 3. AI Lifecycle Controls | B16: M3.4 | C16: Human oversight & intervention | D16: AIRG Consultation Paper P017-2025 (Nov 2025, proposed) | E16: A.9.2; A.9.3; A.9.4 | F16: GOVERN 3.2; MAP 3.5 | G16: Model Owner + InfoSec | H16: Not started | J16: Human oversight policy | N16: Play 4 | O16: MGF D2.3, D2.4, D2.6 | SAFR S2.3 | R16: —
A17: 3. AI Lifecycle Controls | B17: M3.5 | C17: Model & feature selection | D17: AI MRM Paper (Dec 2024); AIRG Consultation Paper P017-2025 (Nov 2025, proposed) | E17: A.4.4; A.6.2.2; A.6.2.3 | F17: MAP 2.1; MAP 3.3 | G17: Model Owner + InfoSec | H17: Not started | J17: Model selection rationale | M17: carry the FEAT/fairness control mappings that feed those principles. | N17: Play 3 | O17: MGF D1.3, D1.4 | SAFR S4.1 | R17: —
A18: 3. AI Lifecycle Controls | B18: M3.6 | C18: Evaluation, testing & independent validation | D18: AI MRM Paper (Dec 2024); AIRG Consultation Paper P017-2025 (Nov 2025, proposed) | E18: A.6.2.4 | F18: MEASURE 1.3; MEASURE 2.3; MEASURE 2.5 | G18: Model Owner + InfoSec | H18: Not started | J18: Validation & test reports | N18: Play 3, 10 | O18: MGF D4.5 | R18: PA 1, PA 11
A19: 3. AI Lifecycle Controls | B19: M3.7 | C19: Technology & cybersecurity controls | D19: AIRG Consultation Paper P017-2025 (Nov 2025, proposed) | E19: A.4.5; A.6.2.3 | F19: MEASURE 2.7 | G19: Model Owner + InfoSec | H19: Not started | J19: Security test results | N19: Play 3 | O19: MGF D3.1, D3.2, D3.3, D3.7 | SAFR S1.3, S1.4, S4.2 | R19: PA 1, PA 3, PA 8, PA 11
A20: 3. AI Lifecycle Controls | B20: M3.8 | C20: Reproducibility, auditability, logging & audit trails | D20: AIRG Consultation Paper P017-2025 (Nov 2025, proposed); MindForge AI Risk Mgmt Toolkit (Mar 2026) | E20: A.4.4; A.6.2.8 | F20: MEASURE 2.1; MANAGE 4.1 | G20: Model Owner + InfoSec | H20: Not started | J20: Logging standards; audit trail | N20: Play 3, 5 | O20: MGF D3.6, D3.13 | SAFR S3.1, S3.2, S3.4 | R20: —
A21: 3. AI Lifecycle Controls | B21: M3.9 | C21: Pre-deployment review & approval (release criteria) | D21: AI MRM Paper (Dec 2024); AIRG Consultation Paper P017-2025 (Nov 2025, proposed) | E21: A.6.2.5 | F21: MANAGE 1.1; MEASURE 2.3 | G21: Model Owner + InfoSec | H21: Not started | J21: Release approval record | N21: Play 4 | R21: —
A22: 3. AI Lifecycle Controls | B22: M3.10 | C22: Post-deployment monitoring (drift, dashboards, revalidation, backtesting) | D22: AI MRM Paper (Dec 2024); AIRG Consultation Paper P017-2025 (Nov 2025, proposed); MindForge AI Risk Mgmt Toolkit (Mar 2026) | E22: A.6.2.6 | F22: MEASURE 2.4; MEASURE 3.1; MANAGE 4.1 | G22: Model Owner + InfoSec | H22: Not started | J22: Monitoring dashboards | N22: Play 5, 11 | O22: MGF D3.11, D3.12, D3.14 | SAFR S2.5, S3.5 | R22: PA 6
A23: 3. AI Lifecycle Controls | B23: M3.11 | C23: Incident management & escalation | D23: AIRG Consultation Paper P017-2025 (Nov 2025, proposed) | E23: A.3.3; A.8.4 | F23: GOVERN 4.3; MEASURE 3.3; MANAGE 4.3 | G23: Model Owner + InfoSec | H23: Not started | J23: Incident playbook | M23: Regulatory notification trigger — FSM-N05 (Technology Risk Management, eff. 10 May 2024; supersedes Notices 644/127/PSN05): notify MAS ≤1 hour of discovering a “relevant incident” (severe/widespread operational or material customer-service impact); root-cause & impact report ≤14 days; 4-hour RTO for critical systems. Confirm exact FSM notice reference for the licence type. (MAS Notice 655 Cyber Hygiene is separate.) | N23: Play 6 | O23: MGF D3.15, D3.16 | SAFR S2.4, S3.5 | R23: PA 10
A24: 3. AI Lifecycle Controls | B24: M3.12 | C24: Change management | D24: AIRG Consultation Paper P017-2025 (Nov 2025, proposed) | E24: A.6.2.2; A.6.2.6 | F24: MANAGE 2.2; MANAGE 4.2 | G24: Model Owner + InfoSec | H24: Not started | J24: Change records | N24: Play 8 | R24: PA 5
A25: 3. AI Lifecycle Controls | B25: M3.13 | C25: Decommissioning / safe phase-out | D25: AIRG Consultation Paper P017-2025 (Nov 2025, proposed) | E25: A.6.2.6 | F25: GOVERN 1.7; MANAGE 2.4 | G25: Model Owner + InfoSec | H25: Not started | J25: Decommissioning checklist | N25: Play 9 | R25: PA 7
A26: 3. AI Lifecycle Controls | B26: M3.14 | C26: Third-party / vendor AI risk management | D26: AI MRM Paper (Dec 2024); AIRG Consultation Paper P017-2025 (Nov 2025, proposed) | E26: A.10.2; A.10.3; A.10.4 | F26: GOVERN 6.1; GOVERN 6.2; MAP 4.1; MANAGE 3.1; MANAGE 3.2 | G26: Model Owner + InfoSec | H26: Not started | J26: Vendor due diligence; contract clauses | N26: Play 7 | O26: MGF D1.6, D3.9 | SAFR S4.4, S4.5 | R26: PA 3
A27: 3. AI Lifecycle Controls | B27: M3.15 | C27: Generative AI & AI-agent risks (hallucination, autonomy, adversarial, concentration) | D27: AIRG Consultation Paper P017-2025 (Nov 2025, proposed); MindForge AI Risk Mgmt Toolkit (Mar 2026) | E27: A.5.5; A.6.2.6 | F27: MAP 5.1; MEASURE 2.6; MEASURE 2.7; MANAGE 2.3 | G27: Model Owner + InfoSec | H27: Not started | J27: GenAI/ agent risk assessment | N27: Play 10 | O27: AGENTIC HINGE → MGF: all D1–D4 | SAFR: all S1–S4 | R27: PA 3
A28: 4. AI Capability & Capacity | B28: M4.1 | C28: Skills, training, resourcing & competency | D28: AIRG Consultation Paper P017-2025 (Nov 2025, proposed); AI MRM Paper (Dec 2024) | E28: A.4.6 | F28: GOVERN 2.2 | G28: AI Risk / HR | H28: Not started | J28: Capability plan; training records | R28: PA 11
A29: 4. AI Capability & Capacity | B29: M4.2 | C29: Technology infrastructure & tooling capacity | D29: AIRG Consultation Paper P017-2025 (Nov 2025, proposed) | E29: A.4.4; A.4.5 | F29: MAP 1.6 | G29: AI Risk / HR | H29: Not started | J29: Infrastructure & tooling plan | R29: PA 5, PA 11
A30: Cross-cutting: FEAT Principles | B30: F1 | C30: Fairness — AIDA decisions do not systematically disadvantage individuals/groups | D30: FEAT (2018) | E30: A.5.4; A.7.4 | F30: MEASURE 2.11 | G30: Compliance | H30: In progress | J30: Fairness Assessment Report (Veritas 3A); fairness-metric results vs thresholds | L30: Annual (high-materiality) + on drift / change | M30: Run per FEAT Assessment Methodology (Veritas-aligned) §A; high-materiality validated per §D. Triggered in Plays 2/3/4; re-tested in Plays 5/8. | N30: Play 2, 3, 4, 5, 8 | R30: —
A31: Cross-cutting: FEAT Principles | B31: F2 | C31: Ethics — AIDA use aligns with organisational ethical standards | D31: FEAT (2018) | E31: A.2.2; A.5.5 | F31: GOVERN 1.2; GOVERN 4.1 | G31: Compliance | H31: In progress | J31: Ethics alignment attestation (Veritas 3B) | L31: Annual + on material change | M31: §B — org-level guiding principles set first; confirmed per use case at Play 2. Reflected in M1.2. | N31: Play 2, 4, 8 | R31: —
A32: Cross-cutting: FEAT Principles | B32: F3 | C32: Accountability — clear internal & external accountability for AIDA-driven decisions | D32: FEAT (2018) | E32: A.3.2; A.10.2 | F32: GOVERN 2.1; GOVERN 2.3 | G32: Compliance | H32: In progress | J32: Accountability matrix; internal authorisation record (Veritas 3B) | L32: Annual + on change | M32: §B — includes third-party model accountability (non-delegable). Anchored in M1.1, M1.3. | N32: Play 2, 4, 8 | O32: MGF D1.5, D2.1 | SAFR S1.1, S3.3 | R32: —
A33: Cross-cutting: FEAT Principles | B33: F4 | C33: Transparency — disclosure & explanation appropriate to each stakeholder | D33: FEAT (2018) | E33: A.8.2; A.8.5; A.6.2.7 | F33: MEASURE 2.8; MEASURE 2.9 | G33: Compliance | H33: In progress | J33: Transparency assessment; model card; customer disclosure standard (Veritas 3C) | L33: Annual + on change | M33: §C — internal + external transparency proportionate to materiality. Triggered Plays 3/4; reviewed Play 8. | N33: Play 2, 3, 4, 5, 8 | O33: MGF D2.7, D4.1 | SAFR S3.2 | R33: —

Sheet Stress-Test Tracker
A1: Stress-Test Tracker — Hotspot Register (10 core + 4 SAFR runtime)
A3: # | B3: Hotspot | C3: Class | D3: Failure mode | E3: Recommended stress tests | F3: Maps to | G3: Owner (role) | H3: Cadence | I3: Last run | J3: Result | K3: Residual risk | L3: Next run
A4: 1 | B4: Generative AI hallucination & factual unreliability | C4: GenAI / Agent | D4: Model emits confident but fabricated or wrong outputs; in an FI context this means mis-stated facts, bad advice, or compliance breaches reaching customers or filings. | E4: Known-answer benchmarks; RAG grounding & citation-faithfulness checks; out-of-distribution and ambiguous prompts; human-graded evals on edge cases; hallucination-rate thresholds. | F4: NIST MEASURE 2.5, 2.9 | ISO A.6.2.4, A.6.2.6 | MAS M3.6, M3.15 | G4: InfoSec + Model Owner | H4: Quarterly + pre-release | J4: Not run
A5: 2 | B5: Prompt injection, jailbreak & data exfiltration | C5: GenAI / Agent | D5: Crafted inputs override instructions, bypass guardrails, leak the system prompt or PII — including indirect injection via retrieved or third-party content. | E5: Red-team injection & jailbreak corpora; indirect/second-order injection via documents and tool outputs; exfiltration canary tokens; guardrail bypass regression suite. | F5: NIST MEASURE 2.7 | ISO A.6.2.3, A.6.2.6 | MAS M3.7, M3.15 | G5: InfoSec + Model Owner | H5: Quarterly + pre-release | I5: 46271 | J5: Fail | K5: High | L5: 46362
A6: 3 | B6: Autonomous agent behaviour & unintended actions | C6: GenAI / Agent | D6: Tool misuse, runaway loops, scope creep, or irreversible actions taken without a human gate; small errors compound across an action chain. | E6: Sandboxed scenario testing; adversarial multi-step task chains; action-space & permission-boundary probes; kill-switch and rollback drills; concentration of authority tests. | F6: NIST MANAGE 2.3, 2.4 | ISO A.9.4, A.6.2.6 | MAS M3.4, M3.15 | G6: InfoSec + Model Owner | H6: Quarterly + pre-release | J6: Not run
A7: 4 | B7: Model drift & performance degradation in production | C7: Classic ML | D7: Data or concept drift silently erodes accuracy; monitoring thresholds fail to trip or are mis-calibrated, so decay goes unnoticed. | E7: Backtesting on shifted time windows; synthetic distribution-shift injection; champion/challenger; validation that drift-alert thresholds actually fire; scheduled revalidation. | F7: NIST MEASURE 2.4, 3.1 | ISO A.6.2.6 | MAS M3.10 | G7: Model Risk + Data Sci | H7: Quarterly | J7: Not run
A8: 5 | B8: Fairness & bias across subgroups | C8: Cross-cutting | D8: Disparate impact on protected or commercial segments; proxy discrimination through correlated features (e.g. postcode as a race proxy). | E8: Slice/subgroup performance; counterfactual fairness tests; proxy-variable analysis; disparate-impact ratio under stressed/underrepresented populations. | F8: NIST MEASURE 2.11 | ISO A.5.4, A.7.4 | MAS M3.2, FEAT F1 | G8: AI Risk + InfoSec | H8: Semi-annual | J8: Not run
A9: 6 | B9: Data quality, lineage & poisoning | C9: Classic ML | D9: Corrupt, unrepresentative or maliciously poisoned data degrades or backdoors the model; broken lineage makes the cause untraceable. | E9: Data-poisoning & label-noise injection; lineage-break detection; missing/corrupt feature injection; representativeness checks under stressed segments. | F9: NIST MAP 2.3, MEASURE 2.1 | ISO A.7.4, A.7.5 | MAS M3.1, M2.3 | G9: Model Risk + Data Sci | H9: Quarterly | J9: Not run
A10: 7 | B10: Robustness to adversarial & edge-case inputs | C10: Classic ML | D10: Small perturbations or rare tail inputs flip outputs; the model is brittle exactly where stakes are high and data is thin. | E10: Adversarial perturbation attacks; boundary & edge-case generation; extreme-value and tail-scenario inputs; input fuzzing; stress at operating-range limits. | F10: NIST MEASURE 2.6, 2.7 | ISO A.6.2.4 | MAS M3.6 | G10: Model Risk + Data Sci | H10: Quarterly | J10: Not run
A11: 8 | B11: Third-party / foundation-model concentration & dependency | C11: Cross-cutting | D11: Vendor model version change, API outage, or silent behaviour shift breaks downstream systems; single-provider reliance creates concentration risk. | E11: Model-swap regression; version-pin drift tests; vendor outage/failover scenarios; behaviour-change detection on upgrades; concentration scenario analysis. | F11: NIST GOVERN 6.2, MANAGE 3.1, 3.2 | ISO A.10.3 | MAS M3.14, M3.15 | G11: AI Risk + InfoSec | H11: Semi-annual | J11: Not run
A12: 9 | B12: Human oversight failure & automation bias | C12: Cross-cutting | D12: Reviewers rubber-stamp AI outputs, override mechanisms go unused, and escalation paths break — oversight exists on paper but not in practice. | E12: Override-rate analysis; seeded-error detection (does the reviewer catch a planted wrong output?); escalation drills; oversight-effectiveness review. | F12: NIST GOVERN 3.2, MAP 3.5 | ISO A.9.2, A.9.3 | MAS M3.4 | G12: AI Risk + InfoSec | H12: Semi-annual | J12: Not run
A13: 10 | B13: Privacy: memorisation, re-identification & inference | C13: Classic ML | D13: Model memorises and regurgitates training PII, or outputs enable re-identification or membership inference of individuals in the training set. | E13: Membership-inference attacks; training-data extraction probes; PII-leakage prompt suites; re-identification testing on aggregated outputs. | F13: NIST MEASURE 2.10 | ISO A.7.2 | MAS M3.1 | G13: Model Risk + Data Sci | H13: Quarterly | J13: Not run
A14: 11 | B14: Disposition-engine latency & fail-open | C14: SAFR / Runtime | D14: The runtime checkpoint adds latency that pressures teams to bypass it, or it fails open (lets actions through) under load or outage — so the control plane becomes a bottleneck or a silent gap at the point of action. | E14: Load/latency injection at the disposition engine under peak volumes; fail-open vs. fail-closed behaviour testing on checkpoint outage; chaos/failover drills on the runtime control plane; timeout and queue-backpressure handling tests. | F14: SAFR S2.1, S2.6 | NIST MANAGE 2.4, MEASURE 2.7 | ISO A.6, A.4 | MAS M3.4 | G14: InfoSec + Technology | H14: Quarterly + pre-release | J14: Not run
A15: 12 | B15: Audit-log tamper-evidence & completeness | C15: SAFR / Runtime | D15: Governance records are incomplete, mutable or tamperable; gaps between executed actions and logged decisions break non-repudiation and leave actions unaccounted for at supervisory review. | E15: Tamper-attempt & integrity-verification tests (append-only / hash-chain); log-completeness reconciliation vs. executed actions; timestamp / clock-manipulation tests; retention and retrievability drills for internal audit and MAS review. | F15: SAFR S3.1, S3.2, S3.4 | NIST MEASURE 3.1, MANAGE 4.1 | ISO A.9, A.8 | MAS M3.15 | G15: InfoSec + Internal Audit | H15: Semi-annual | J15: Not run
A16: 13 | B16: Mandate bypass & stale controls-repository | C16: SAFR / Runtime | D16: An agent executes actions outside its granted mandate, or the controls repository is stale / misconfigured so thresholds and policies are not enforced at runtime. | E16: Out-of-mandate action injection (does the pre-execution check block it?); threshold-boundary probes; stale / rolled-back policy-version tests; privilege-escalation and mandate scope-creep chains. | F16: SAFR S1.2, S1.3, S1.4 | NIST MANAGE 2.3, GOVERN 1.3 | ISO A.9, A.2 | MAS M3.4 | G16: AI Risk + InfoSec | H16: Quarterly + pre-release | J16: Not run
A17: 14 | B17: Gateway coverage & cross-system enforcement gaps | C17: SAFR / Runtime | D17: Agent actions route around the gateway or native embedding, or enforcement is inconsistent across downstream systems — leaving unchecked execution paths, including for third-party agents. | E17: Coverage / attack-surface mapping for actions that evade interception; direct-API and side-channel path tests; cross-system consistency checks (same mandate enforced everywhere); third-party / vendor agent path coverage. | F17: SAFR S4.2, S4.4, S4.5 | NIST MANAGE 2.3, 3.1 | ISO A.9, A.10 | MAS M3.14 | G17: InfoSec + Technology | H17: Semi-annual | J17: Not run

Sheet Maturity Dashboard
B2: AI Governance — Maturity & Readiness Dashboard
B3: Live roll-up of the control trackers. Update Status & Maturity on each Control Library tab and these figures refresh automatically.
B5: Framework | C5: # Controls | D5: Not started | E5: In progress | F5: Implemented | G5: Operating effectively | H5: N/A | I5: Avg maturity | J5: % Implemented+
B6: ISO 42001 | C6: 38 | D6: =COUNTIF('Control Library - ISO 42001'!F4:F41,"Not started") | E6: =COUNTIF('Control Library - ISO 42001'!F4:F41,"In progress") | F6: =COUNTIF('Control Library - ISO 42001'!F4:F41,"Implemented") | G6: =COUNTIF('Control Library - ISO 42001'!F4:F41,"Operating effectively") | H6: =COUNTIF('Control Library - ISO 42001'!F4:F41,"Not applicable") | I6: =IFERROR(ROUND(AVERAGE('Control Library - ISO 42001'!G4:G41),2),"-") | J6: =IFERROR(ROUND((COUNTIF('Control Library - ISO 42001'!F4:F41,"Implemented")+COUNTIF('Control Library - ISO 42001'!F4:F41,"Operating effectively"))/(38-COUNTIF('Control Library - ISO 42001'!F4:F41,"Not applicable")),3),0)
B7: NIST AI RMF | C7: 72 | D7: =COUNTIF('Control Library - NIST AI RMF'!G4:G75,"Not started") | E7: =COUNTIF('Control Library - NIST AI RMF'!G4:G75,"In progress") | F7: =COUNTIF('Control Library - NIST AI RMF'!G4:G75,"Implemented") | G7: =COUNTIF('Control Library - NIST AI RMF'!G4:G75,"Operating effectively") | H7: =COUNTIF('Control Library - NIST AI RMF'!G4:G75,"Not applicable") | I7: =IFERROR(ROUND(AVERAGE('Control Library - NIST AI RMF'!H4:H75),2),"-") | J7: =IFERROR(ROUND((COUNTIF('Control Library - NIST AI RMF'!G4:G75,"Implemented")+COUNTIF('Control Library - NIST AI RMF'!G4:G75,"Operating effectively"))/(72-COUNTIF('Control Library - NIST AI RMF'!G4:G75,"Not applicable")),3),0)
B8: MAS | C8: 30 | D8: =COUNTIF('Control Library - MAS'!H4:H33,"Not started") | E8: =COUNTIF('Control Library - MAS'!H4:H33,"In progress") | F8: =COUNTIF('Control Library - MAS'!H4:H33,"Implemented") | G8: =COUNTIF('Control Library - MAS'!H4:H33,"Operating effectively") | H8: =COUNTIF('Control Library - MAS'!H4:H33,"Not applicable") | I8: =IFERROR(ROUND(AVERAGE('Control Library - MAS'!I4:I33),2),"-") | J8: =IFERROR(ROUND((COUNTIF('Control Library - MAS'!H4:H33,"Implemented")+COUNTIF('Control Library - MAS'!H4:H33,"Operating effectively"))/(30-COUNTIF('Control Library - MAS'!H4:H33,"Not applicable")),3),0)
B9: IMDA MGF Agentic | C9: 34 | D9: =COUNTIF('Control Library - MGF Agentic'!I4:I37,"Not started") | E9: =COUNTIF('Control Library - MGF Agentic'!I4:I37,"In progress") | F9: =COUNTIF('Control Library - MGF Agentic'!I4:I37,"Implemented") | G9: =COUNTIF('Control Library - MGF Agentic'!I4:I37,"Operating effectively") | H9: =COUNTIF('Control Library - MGF Agentic'!I4:I37,"Not applicable") | I9: =IFERROR(ROUND(AVERAGE('Control Library - MGF Agentic'!J4:J37),2),"-") | J9: =IFERROR(ROUND((COUNTIF('Control Library - MGF Agentic'!I4:I37,"Implemented")+COUNTIF('Control Library - MGF Agentic'!I4:I37,"Operating effectively"))/(34-COUNTIF('Control Library - MGF Agentic'!I4:I37,"Not applicable")),3),0)
B10: SAFR (Runtime) | C10: 21 | D10: =COUNTIF('Control Library - SAFR'!I4:I24,"Not started") | E10: =COUNTIF('Control Library - SAFR'!I4:I24,"In progress") | F10: =COUNTIF('Control Library - SAFR'!I4:I24,"Implemented") | G10: =COUNTIF('Control Library - SAFR'!I4:I24,"Operating effectively") | H10: =COUNTIF('Control Library - SAFR'!I4:I24,"Not applicable") | I10: =IFERROR(ROUND(AVERAGE('Control Library - SAFR'!J4:J24),2),"-") | J10: =IFERROR(ROUND((COUNTIF('Control Library - SAFR'!I4:I24,"Implemented")+COUNTIF('Control Library - SAFR'!I4:I24,"Operating effectively"))/(C10-COUNTIF('Control Library - SAFR'!I4:I24,"Not applicable")),3),0)
B11: TOTAL | C11: =SUM(C6:C10) | D11: =SUM(D6:D10) | E11: =SUM(E6:E10) | F11: =SUM(F6:F10) | G11: =SUM(G6:G10) | H11: =SUM(H6:H10) | I11: =IFERROR(ROUND(AVERAGE(I6:I10),2),"-") | J11: =IFERROR((F11+G11)/(C11-H11),0)
B13: Status values
B14: Not started / In progress / Implemented / Operating effectively / Not applicable
B15: Maturity scale
B16: 1 Initial • 2 Developing • 3 Defined • 4 Managed • 5 Optimised
B17: % Implemented+ = (Implemented + Operating effectively) / (controls excluding N/A)
B19: FEAT OPERATIONALISATION
B20: All four FEAT principles assessed, evidenced (Veritas) and triggered by the plays. Principles operationalised: | F20: =COUNTIF('Control Library - MAS'!H30:H33,"<>Not started")&" / 4"
B21: Principle | C21: Status (live) | D21: Triggered in plays | E21: Evidence (Veritas) | F21: Review cadence
B22: Fairness (F1) | C22: ='Control Library - MAS'!H30 | D22: 2, 3, 4, 5, 8 | E22: Doc 3A — Fairness Report | F22: Annual + drift
B23: Ethics (F2) | C23: ='Control Library - MAS'!H31 | D23: 2, 4, 8 | E23: Doc 3B — Ethics attestation | F23: Annual
B24: Accountability (F3) | C24: ='Control Library - MAS'!H32 | D24: 2, 4, 8 | E24: Doc 3B — Accountability matrix | F24: Annual
B25: Transparency (F4) | C25: ='Control Library - MAS'!H33 | D25: 2, 3, 4, 5, 8
B26: Methodology: FEAT Assessment Methodology (Veritas-aligned) — §A Fairness, §B Ethics & Accountability, §C Transparency, §D high-materiality validation.
B28: ASSURANCE TESTING — TEST OF DESIGN & OPERATING EFFECTIVENESS
B29: Framework | C29: Design assessed | D29: Design adequate | E29: % design adequate | F29: Operating assessed | G29: Operating effective | H29: % operating effective
B30: ISO 42001 | C30: =COUNTIF('Control Library - ISO 42001'!M4:M41,"Adequate")+COUNTIF('Control Library - ISO 42001'!M4:M41,"Partially adequate")+COUNTIF('Control Library - ISO 42001'!M4:M41,"Inadequate") | D30: =COUNTIF('Control Library - ISO 42001'!M4:M41,"Adequate") | E30: =IFERROR(D30/C30,0) | F30: =COUNTIF('Control Library - ISO 42001'!N4:N41,"Effective")+COUNTIF('Control Library - ISO 42001'!N4:N41,"Partially effective")+COUNTIF('Control Library - ISO 42001'!N4:N41,"Ineffective") | G30: =COUNTIF('Control Library - ISO 42001'!N4:N41,"Effective") | H30: =IFERROR(G30/F30,0)
B31: NIST AI RMF | C31: =COUNTIF('Control Library - NIST AI RMF'!N4:N75,"Adequate")+COUNTIF('Control Library - NIST AI RMF'!N4:N75,"Partially adequate")+COUNTIF('Control Library - NIST AI RMF'!N4:N75,"Inadequate") | D31: =COUNTIF('Control Library - NIST AI RMF'!N4:N75,"Adequate") | E31: =IFERROR(D31/C31,0) | F31: =COUNTIF('Control Library - NIST AI RMF'!O4:O75,"Effective")+COUNTIF('Control Library - NIST AI RMF'!O4:O75,"Partially effective")+COUNTIF('Control Library - NIST AI RMF'!O4:O75,"Ineffective") | G31: =COUNTIF('Control Library - NIST AI RMF'!O4:O75,"Effective") | H31: =IFERROR(G31/F31,0)
B32: MAS | C32: =COUNTIF('Control Library - MAS'!P4:P33,"Adequate")+COUNTIF('Control Library - MAS'!P4:P33,"Partially adequate")+COUNTIF('Control Library - MAS'!P4:P33,"Inadequate") | D32: =COUNTIF('Control Library - MAS'!P4:P33,"Adequate") | E32: =IFERROR(D32/C32,0) | F32: =COUNTIF('Control Library - MAS'!Q4:Q33,"Effective")+COUNTIF('Control Library - MAS'!Q4:Q33,"Partially effective")+COUNTIF('Control Library - MAS'!Q4:Q33,"Ineffective") | G32: =COUNTIF('Control Library - MAS'!Q4:Q33,"Effective") | H32: =IFERROR(G32/F32,0)
B33: IMDA MGF Agentic | C33: =COUNTIF('Control Library - MGF Agentic'!S4:S37,"Adequate")+COUNTIF('Control Library - MGF Agentic'!S4:S37,"Partially adequate")+COUNTIF('Control Library - MGF Agentic'!S4:S37,"Inadequate") | D33: =COUNTIF('Control Library - MGF Agentic'!S4:S37,"Adequate") | E33: =IFERROR(D33/C33,0) | F33: =COUNTIF('Control Library - MGF Agentic'!T4:T37,"Effective")+COUNTIF('Control Library - MGF Agentic'!T4:T37,"Partially effective")+COUNTIF('Control Library - MGF Agentic'!T4:T37,"Ineffective") | G33: =COUNTIF('Control Library - MGF Agentic'!T4:T37,"Effective") | H33: =IFERROR(G33/F33,0)
B34: SAFR (Runtime) | C34: =COUNTIF('Control Library - SAFR'!T4:T24,"Adequate")+COUNTIF('Control Library - SAFR'!T4:T24,"Partially adequate")+COUNTIF('Control Library - SAFR'!T4:T24,"Inadequate") | D34: =COUNTIF('Control Library - SAFR'!T4:T24,"Adequate") | E34: =IFERROR(D34/C34,0) | F34: =COUNTIF('Control Library - SAFR'!U4:U24,"Effective")+COUNTIF('Control Library - SAFR'!U4:U24,"Partially effective")+COUNTIF('Control Library - SAFR'!U4:U24,"Ineffective") | G34: =COUNTIF('Control Library - SAFR'!U4:U24,"Effective") | H34: =IFERROR(G34/F34,0)
B35: TOTAL | C35: =SUM(C30:C34) | D35: =SUM(D30:D34) | E35: =IFERROR(D35/C35,0) | F35: =SUM(F30:F34) | G35: =SUM(G30:G34) | H35: =IFERROR(G35/F35,0)
B37: Test of Design conclusions: Not tested / Adequate / Partially adequate / Inadequate / Not applicable. Test of Operating Effectiveness: Not tested / Effective / Partially effective / Ineffective / Not applicable. % columns are of the assessed (tested) population. ToD is the evidentiary basis for an 'Implemented' status; ToE for 'Operating effectively'.

Sheet Control Library - MGF Agentic
A1: Control Library - IMDA MGF for Agentic AI — Control Tracker
A3: Dimension | B3: MGF Control ID | C3: Control / Recommended Measure | D3: Objective — what it bounds | E3: MAS AIRG theme | F3: ISO/IEC 42001 Annex A | G3: NIST AI RMF | H3: Owner (role) | I3: Status | J3: Maturity (1-5) | K3: Evidence / artifact | L3: Last reviewed | M3: Next review | N3: Gap / notes | O3: Weight (1-5) | P3: Weighted maturity | Q3: Linked play | R3: Linked MAS | SAFR | S3: Test of Design | T3: Test of Operating Effectiveness | U3: Linked CSA PA
A4: D1 Bound risk | B4: D1.1 | C4: Use-case suitability assessment | D4: Stop agents being deployed in unsuitable / high-impact contexts | E4: AI Inventory & Materiality | F4: A.5 Impact assessment | G4: MAP 1.1, 1.6 | H4: AI Risk (2nd line) / Model Owner | I4: Not started | O4: 5 | P4: =IF(J4="","",O4*J4) | Q4: Play 1, 2 | R4: MAS M2.3 | SAFR S1.5 | U4: PA 7
A5: D1 Bound risk | B5: D1.2 ★ | C5: Tiered risk classification | D5: Right-size controls to the level of risk | E5: AI Inventory & Materiality | F5: A.5 Impact assessment | G5: MAP 1.5, 2.2 | H5: AI Risk (2nd line) / Model Owner | I5: Not started | O5: 4 | P5: =IF(J5="","",O5*J5) | Q5: Play 1, 8 | R5: MAS M2.3 | U5: —
A6: D1 Bound risk | B6: D1.3 | C6: Define agent limits at design | D6: Cap the agent's blast radius before build | E6: Lifecycle: Development & Validation | F6: A.6 AI system life cycle | G6: MAP 2.1; MANAGE 1.3 | H6: AI Risk (2nd line) / Model Owner | I6: Not started | O6: 5 | P6: =IF(J6="","",O6*J6) | Q6: Play 3 | R6: MAS M3.5 | SAFR S1.2 | U6: PA 3
A7: D1 Bound risk | B7: D1.4 | C7: Least-privilege access (scoping) | D7: Limit reachable systems and data | E7: Lifecycle: Development & Validation | F7: A.6 AI system life cycle | G7: MANAGE 2.3; MEASURE 2.7 | H7: Model Developer / InfoSec | I7: Not started | O7: 5 | P7: =IF(J7="","",O7*J7) | Q7: Play 3 | R7: MAS M3.5, M3.7 | SAFR S1.4 | U7: PA 3
A8: D1 Bound risk | B8: D1.5 | C8: Agent identity management (identity card + authorisation trail) | D8: Give every agent a verifiable identity — capabilities, limits, authorised action domains and escalation — plus a trail of which agent acted under whose authority, so every action is attributable. | E8: Oversight & Accountability | F8: A.3 Internal organisation | G8: GOVERN 2.1; MAP 1.1; MEASURE 3.1 | H8: AI Risk (2nd line) / Model Owner | I8: Not started | O8: 5 | P8: =IF(J8="","",O8*J8) | Q8: Play 2, 7, 9 | R8: MAS M3.8, F3 | SAFR S1.1, S3.3 | U8: PA 3
A9: D1 Bound risk | B9: D1.6 ★ | C9: Third-party / multi-agent dependency review | D9: Bound risk inherited from external / peer agents | E9: Third-Party & Reliance Risk | F9: A.10 Third-party relationships | G9: GOVERN 6.1; MANAGE 3.1 | H9: AI Risk (2nd line) / Model Owner | I9: Not started | O9: 4 | P9: =IF(J9="","",O9*J9) | Q9: Play 1, 7 | R9: MAS M3.14 | SAFR S4.4, S4.5 | U9: PA 3, PA 7
A10: D2 Human accountability | B10: D2.1 | C10: Responsibility allocation across value chain | D10: Keep a named owner answerable for agent actions | E10: Oversight & Accountability | F10: A.3 Internal organisation | G10: GOVERN 2.1, 2.3 | H10: AI Risk Cttee / AI Risk (2nd line) | I10: Not started | O10: 5 | P10: =IF(J10="","",O10*J10) | Q10: Play 1, All | R10: MAS M1.1, F3 | SAFR S1.2 | U10: PA 2
A11: D2 Human accountability | B11: D2.2 | C11: Adaptive governance | D11: Keep governance current with capability change | E11: Oversight & Accountability | F11: A.6 AI system life cycle | G11: GOVERN 1.3, 4.3 | H11: AI Risk Cttee / AI Risk (2nd line) | I11: Not started | O11: 3 | P11: =IF(J11="","",O11*J11) | Q11: Play 8 | U11: PA 4
A12: D2 Human accountability | B12: D2.3 | C12: Human approval at significant checkpoints | D12: Hold the agent at the points that matter most | E12: Oversight & Accountability | F12: A.6 AI system life cycle | G12: GOVERN 4.1; MANAGE 2.3 | H12: AI Risk Committee / Model Owner | I12: Not started | O12: 5 | P12: =IF(J12="","",O12*J12) | Q12: Play 4 | R12: MAS M3.4 | SAFR S2.3 | U12: —
A13: D2 Human accountability | B13: D2.4 | C13: Approval design | D13: Prevent oversight collapsing into rubber-stamping | E13: Oversight & Accountability | F13: A.6 AI system life cycle | G13: GOVERN 4.1; MEASURE 3.3 | H13: AI Risk Committee / Model Owner | I13: Not started | O13: 4 | P13: =IF(J13="","",O13*J13) | Q13: Play 4 | R13: MAS M3.4 | SAFR S2.3 | U13: —
A14: D2 Human accountability | B14: D2.5 | C14: Audit approval effectiveness | D14: Verify oversight is real, not nominal | E14: Oversight & Accountability | F14: A.6 AI system life cycle | G14: MEASURE 4.1; MANAGE 4.1 | H14: AI Risk Committee / Model Owner | I14: Not started | O14: 4 | P14: =IF(J14="","",O14*J14) | Q14: Play 5, 11 | R14: MAS M3.4 | SAFR S3.5 | U14: PA 6
A15: D2 Human accountability | B15: D2.6 ★ | C15: Automation-bias countermeasures | D15: Detect decaying human attention early | E15: Oversight & Accountability | F15: A.6 AI system life cycle | G15: GOVERN 3.2; MEASURE 3.3 | H15: AI Risk Committee / Model Owner | I15: Not started | O15: 4 | P15: =IF(J15="","",O15*J15) | Q15: Play 11 | R15: MAS M3.4 | U15: PA 10
A16: D2 Human accountability | B16: D2.7 | C16: End-user accountability information | D16: Enable accountability to flow to users | E16: Transparency & Communication | F16: A.8 Information to interested parties | G16: GOVERN 5.1; MAP 3.5 | H16: Compliance & Legal | I16: Not started | O16: 3 | P16: =IF(J16="","",O16*J16) | Q16: Play 11 | R16: MAS M3.3, F4 | SAFR S3.2 | U16: —
A17: D3 Technical controls | B17: D3.1 | C17: Least-privilege tool/data access (technical) | D17: Constrain capability at runtime | E17: Lifecycle: Development & Validation | F17: A.6 AI system life cycle | G17: MANAGE 2.3; MEASURE 2.7 | H17: Model Developer / InfoSec | I17: Not started | O17: 5 | P17: =IF(J17="","",O17*J17) | Q17: Play 3 | R17: MAS M3.7 | SAFR S1.4 | U17: PA 3, PA 8
A18: D3 Technical controls | B18: D3.2 | C18: Secure sandboxed environment | D18: Contain agents during build/test | E18: Lifecycle: Development & Validation | F18: A.6 AI system life cycle | G18: MANAGE 2.3; MEASURE 2.7 | H18: Model Developer / InfoSec | I18: Not started | O18: 4 | P18: =IF(J18="","",O18*J18) | Q18: Play 3 | R18: MAS M3.7 | SAFR S2.6 | U18: PA 3, PA 8
A19: D3 Technical controls | B19: D3.3 | C19: Tool guardrails | D19: Prevent tool misuse or invented tool calls | E19: Lifecycle: Development & Validation | F19: A.6 AI system life cycle | G19: MANAGE 2.3, 2.4 | H19: Model Developer / InfoSec | I19: Not started | O19: 4 | P19: =IF(J19="","",O19*J19) | Q19: Play 3 | R19: MAS M3.7 | SAFR S2.4 | U19: PA 3, PA 8
A20: D3 Technical controls | B20: D3.4 | C20: Plan reflection | D20: Catch flawed plans before execution | E20: Lifecycle: Development & Validation | F20: A.6 AI system life cycle | G20: MEASURE 2.5; MANAGE 1.3 | H20: Model Developer / InfoSec | I20: Not started | O20: 3 | P20: =IF(J20="","",O20*J20) | Q20: Play 3 | U20: —
A21: D3 Technical controls | B21: D3.5 | C21: Instruction comprehension check | D21: Reduce mis-scoped task execution | E21: Lifecycle: Development & Validation | F21: A.6 AI system life cycle | G21: MEASURE 2.5 | H21: Model Developer / InfoSec | I21: Not started | O21: 3 | P21: =IF(J21="","",O21*J21) | Q21: Play 3 | U21: —
A22: D3 Technical controls | B22: D3.6 | C22: Plan & reasoning logging | D22: Make agent intent inspectable | E22: Lifecycle: Deployment & Monitoring | F22: A.6 AI system life cycle | G22: MEASURE 3.1; MAP 1.1 | H22: Model Owner / AI Risk (2nd line) | I22: Not started | O22: 4 | P22: =IF(J22="","",O22*J22) | Q22: Play 3, 5 | R22: MAS M3.8 | SAFR S3.1 | U22: —
A23: D3 Technical controls | B23: D3.7 ★ | C23: Structural / rule-based controls | D23: Use controls that can't be prompted away | E23: Lifecycle: Development & Validation | F23: A.6 AI system life cycle | G23: MANAGE 2.3; MEASURE 2.7 | H23: Model Developer / InfoSec | I23: Not started | O23: 5 | P23: =IF(J23="","",O23*J23) | Q23: Play 3 | R23: MAS M3.7 | SAFR S1.4 | U23: PA 3, PA 8
A24: D3 Technical controls | B24: D3.8 | C24: Agent-specific testing | D24: Validate the agent before release | E24: Lifecycle: Development & Validation | F24: A.6 AI system life cycle | G24: MEASURE 1.3, 2.3 | H24: Independent Validation / InfoSec | I24: Not started | O24: 5 | P24: =IF(J24="","",O24*J24) | Q24: Play 3, 10 | U24: PA 1, PA 11
A25: D3 Technical controls | B25: D3.9 ★ | C25: Multi-agent / workflow evaluation | D25: Surface emergent multi-agent failure | E25: Lifecycle: Development & Validation | F25: A.6 AI system life cycle | G25: MEASURE 2.6; MANAGE 3.1 | H25: Independent Validation / InfoSec | I25: Not started | O25: 4 | P25: =IF(J25="","",O25*J25) | Q25: Play 3, 10 | R25: MAS M3.14 | SAFR S4.4 | U25: PA 1
A26: D3 Technical controls | B26: D3.10 | C26: Gradual rollout | D26: Contain impact of unseen failures | E26: Lifecycle: Deployment & Monitoring | F26: A.6 AI system life cycle | G26: MANAGE 1.3, 2.4 | H26: Model Owner | I26: Not started | O26: 4 | P26: =IF(J26="","",O26*J26) | Q26: Play 4 | U26: PA 5
A27: D3 Technical controls | B27: D3.11 | C27: Continuous monitoring + real-time intervention | D27: Stop harm as it emerges | E27: Lifecycle: Deployment & Monitoring | F27: A.6 AI system life cycle | G27: MEASURE 2.4; MANAGE 4.1 | H27: Model Owner / AI Risk (2nd line) | I27: Not started | O27: 5 | P27: =IF(J27="","",O27*J27) | Q27: Play 5 | R27: MAS M3.10 | SAFR S2.5 | U27: PA 3, PA 9, PA 10
A28: D3 Technical controls | B28: D3.12 | C28: Anomaly detection | D28: Flag deviation from expected behaviour | E28: Lifecycle: Deployment & Monitoring | F28: A.6 AI system life cycle | G28: MEASURE 2.4, 3.1 | H28: Model Owner / AI Risk (2nd line) | I28: Not started | O28: 4 | P28: =IF(J28="","",O28*J28) | Q28: Play 5 | R28: MAS M3.10 | SAFR S2.5 | U28: PA 9
A29: D3 Technical controls | B29: D3.13 | C29: Logging strategy | D29: Ensure the right evidence exists | E29: Lifecycle: Deployment & Monitoring | F29: A.6 AI system life cycle | G29: MEASURE 3.1; MANAGE 4.1 | H29: Model Owner / AI Risk (2nd line) | I29: Not started | O29: 4 | P29: =IF(J29="","",O29*J29) | Q29: Play 5 | R29: MAS M3.8 | SAFR S3.1, S3.2 | U29: —
A30: D3 Technical controls | B30: D3.14 | C30: Log monitoring & alerting | D30: Turn logs into timely action | E30: Lifecycle: Deployment & Monitoring | F30: A.6 AI system life cycle | G30: MEASURE 3.3; MANAGE 4.1 | H30: Model Owner / AI Risk (2nd line) | I30: Not started | O30: 4 | P30: =IF(J30="","",O30*J30) | Q30: Play 5 | R30: MAS M3.10 | SAFR S3.5 | U30: —
A31: D3 Technical controls | B31: D3.15 | C31: Incident review & periodic audit | D31: Assure ongoing fitness of the system | E31: Lifecycle: Deployment & Monitoring | F31: A.6 AI system life cycle | G31: MANAGE 4.1, 4.3 | H31: Model Owner / AI Risk (2nd line) | I31: Not started | O31: 4 | P31: =IF(J31="","",O31*J31) | Q31: Play 5, 6 | R31: MAS M3.11 | SAFR S3.5 | U31: PA 11
A32: D3 Technical controls | B32: D3.16 | C32: Emergent-risk response mechanisms | D32: Be ready for the unforeseen | E32: Lifecycle: Deployment & Monitoring | F32: A.6 AI system life cycle | G32: MANAGE 4.1, 4.2 | H32: Model Owner / AI Risk (2nd line) | I32: Not started | O32: 3 | P32: =IF(J32="","",O32*J32) | Q32: Play 5, 6 | R32: MAS M3.11 | SAFR S2.6 | U32: PA 10
A33: D4 End-user responsibility | B33: D4.1 | C33: Transparency to interacting users | D33: Let users understand who/what they deal with | E33: Transparency & Communication | F33: A.8 Information to interested parties | G33: GOVERN 5.1; MAP 3.5 | H33: Model Owner / Compliance | I33: Not started | O33: 3 | P33: =IF(J33="","",O33*J33) | Q33: Play 11 | R33: MAS M3.3, F4 | SAFR S3.2 | U33: —
A34: D4 End-user responsibility | B34: D4.2 | C34: Transparency to integrating users | D34: Inform those who build on the agent | E34: Transparency & Communication | F34: A.8 Information to interested parties | G34: GOVERN 5.1; MAP 3.4 | H34: Model Owner / Compliance | I34: Not started | O34: 3 | P34: =IF(J34="","",O34*J34) | Q34: Play 11 | R34: MAS M3.3 | U34: —
A35: D4 End-user responsibility | B35: D4.3 | C35: Oversight training | D35: Build competent human oversight | E35: Capabilities & Competency | F35: A.4 Resources | G35: GOVERN 2.2 | H35: Model Owner / HR (capability) | I35: Not started | O35: 4 | P35: =IF(J35="","",O35*J35) | Q35: Play 11 | R35: MAS M1.5, M4.1 | U35: —
A36: D4 End-user responsibility | B36: D4.4 ★ | C36: Tradecraft preservation | D36: Keep humans able to take over | E36: Capabilities & Competency | F36: A.4 Resources | G36: GOVERN 2.2; MANAGE 4.1 | H36: Model Owner / HR (capability) | I36: Not started | O36: 3 | P36: =IF(J36="","",O36*J36) | Q36: Play 11 | R36: MAS M1.5 | U36: —
A37: D4 End-user responsibility | B37: D4.5 | C37: End-user as auditor / red-teamer | D37: Add a human assurance layer | E37: Capabilities & Competency | F37: A.6 AI system life cycle | G37: MEASURE 1.1; MANAGE 4.3 | H37: InfoSec / AI Risk | I37: Not started | O37: 3 | P37: =IF(J37="","",O37*J37) | Q37: Play 10, 11 | R37: MAS M3.6 | U37: —
A39: ★ = control emphasised in IMDA MGF for Agentic AI v1.0 (Jan 2026), updated 20 May 2026. Weight = criticality (seeded default, tune to risk appetite). Weighted maturity = Weight × Maturity.

Sheet Control Library - SAFR
A1: Control Library - SAFR (Safeguards for Agentic Finance at Runtime) — Control Tracker
A3: Dimension | B3: SAFR Control ID | C3: Control / recommended measure | D3: Objective — what it bounds | E3: MAS AIRG theme | F3: ISO/IEC 42001 Annex A | G3: NIST AI RMF | H3: Owner (role) | I3: Status | J3: Maturity (1-5) | K3: Evidence / artifact | L3: Last reviewed | M3: Next review | N3: Gap / notes | O3: Weight (1-5) | P3: Weighted maturity | Q3: Linked play | R3: Linked stress test | S3: Linked MAS | MGF | T3: Test of Design | U3: Test of Operating Effectiveness | V3: Linked CSA PA
A4: S1 Policy-bound execution | B4: S1.1 ★ | C4: Agent identity & registration | D4: Ensure every acting agent is uniquely identified and registered before it can transact | E4: AI Inventory & Materiality | F4: A.3 Roles & responsibilities; A.9 Use of AI systems | G4: GOVERN 2.1; MAP 1.1 | H4: InfoSec / AI Risk (2nd line) | I4: Not started | O4: 5 | P4: =IF(J4="","",O4*J4) | Q4: Play 1, 11 | S4: MAS F3 | MGF D1.5 | V4: PA 3
A5: S1 Policy-bound execution | B5: S1.2 ★ | C5: Agent mandate definition | D5: Grant each agent an explicit, bounded authority — permitted actions, counterparties, value/exposure limits | E5: Lifecycle: Development & Validation | F5: A.6 AI system life cycle; A.9 | G5: GOVERN 1.3; MANAGE 1.3 | H5: Model Owner / AI Risk (2nd line) | I5: Not started | O5: 5 | P5: =IF(J5="","",O5*J5) | Q5: Play 3, 11 | R5: ST-13 | S5: MAS M2.3 | MGF D1.3, D2.1 | V5: PA 3
A6: S1 Policy-bound execution | B6: S1.3 ★ | C6: Institutional controls repository | D6: Encode policies, rules and risk thresholds in a queryable repository the runtime checks against | E6: Governance & Oversight | F6: A.2 AI policy; A.4 Resources | G6: GOVERN 1.1, 4.1 | H6: AI Risk (2nd line) | I6: Not started | O6: 5 | P6: =IF(J6="","",O6*J6) | Q6: Play 11 | R6: ST-13 | S6: MAS M3.7 | MGF D3.1 | V6: —
A7: S1 Policy-bound execution | B7: S1.4 ★ | C7: Pre-execution authority check | D7: Test every proposed action against the agent's mandate before it executes | E7: Governance & Oversight | F7: A.9 Use of AI systems | G7: MANAGE 2.3; MEASURE 3.1 | H7: InfoSec / Model Owner | I7: Not started | O7: 5 | P7: =IF(J7="","",O7*J7) | Q7: Play 11 | R7: ST-13 | S7: MAS M3.7 | MGF D1.4, D3.1, D3.7 | V7: PA 3
A8: S1 Policy-bound execution | B8: S1.5 | C8: Risk-threshold binding | D8: Bind monetary, exposure and sensitivity thresholds to the pre-execution check | E8: AI Inventory & Materiality | F8: A.5 Impact assessment | G8: MAP 2.3; MANAGE 1.3 | H8: AI Risk (2nd line) / Model Owner | I8: Not started | O8: 4 | P8: =IF(J8="","",O8*J8) | Q8: Play 1, 11 | S8: MAS M2.3 | MGF D1.1 | V8: —
A9: S2 Real-time validation | B9: S2.1 ★ | C9: Disposition engine | D9: Evaluate each proposed action at runtime and assign a disposition before execution | E9: Governance & Oversight | F9: A.6 AI system life cycle; A.9 | G9: MEASURE 2.7; MANAGE 2.3 | H9: InfoSec / Model Owner | I9: Not started | O9: 5 | P9: =IF(J9="","",O9*J9) | Q9: Play 11 | R9: ST-11 | S9: MAS M3.4 | MGF D3.11 | V9: PA 10
A10: S2 Real-time validation | B10: S2.2 | C10: Automated approval path | D10: Auto-execute actions that fall within mandate and thresholds | E10: Lifecycle: Deployment | F10: A.9 Use of AI systems | G10: MANAGE 2.4 | H10: Model Owner | I10: Not started | O10: 3 | P10: =IF(J10="","",O10*J10) | Q10: Play 11 | S10: MAS M3.4 | MGF D2.3 | V10: —
A11: S2 Real-time validation | B11: S2.3 ★ | C11: Human-in-the-loop escalation | D11: Route out-of-bounds or ambiguous actions to a named human for review before execution | E11: Human Oversight | F11: A.9; A.8 Information for interested parties | G11: GOVERN 4.1; MANAGE 2.3 | H11: Model Owner / AI Risk Committee | I11: Not started | O11: 5 | P11: =IF(J11="","",O11*J11) | Q11: Play 11 | S11: MAS M3.4 | MGF D2.3, D2.4 | V11: PA 3, PA 10
A12: S2 Real-time validation | B12: S2.4 | C12: Reject / block path | D12: Block actions outside mandate at the point of action | E12: Governance & Oversight | F12: A.9 Use of AI systems | G12: MANAGE 2.3 | H12: InfoSec | I12: Not started | O12: 4 | P12: =IF(J12="","",O12*J12) | Q12: Play 6, 11 | S12: MAS M3.11 | MGF D3.3 | V12: PA 10
A13: S2 Real-time validation | B13: S2.5 | C13: Proceed-and-flag path | D13: Permit lower-risk actions to proceed while flagging them for monitoring | E13: Monitoring | F13: A.6 AI system life cycle | G13: MEASURE 4.1; MANAGE 4.1 | H13: Model Owner / AI Risk (2nd line) | I13: Not started | O13: 3 | P13: =IF(J13="","",O13*J13) | Q13: Play 5, 11 | S13: MAS M3.10 | MGF D3.11, D3.12 | V13: PA 9
A14: S2 Real-time validation | B14: S2.6 | C14: Checkpoint resilience | D14: Ensure the runtime checkpoint is highly available and not itself a single point of failure | E14: Operational Resilience | F14: A.6; A.4 Resources | G14: MANAGE 2.4; MEASURE 2.7 | H14: InfoSec / Technology | I14: Not started | O14: 4 | P14: =IF(J14="","",O14*J14) | Q14: Play 5, 11 | R14: ST-11 | S14: MAS M3.10 | MGF D3.16 | V14: —
A15: S3 Auditability | B15: S3.1 ★ | C15: Tamper-evident audit log | D15: Record each governance decision in an immutable, tamper-evident log | E15: Records & Auditability | F15: A.9; A.4 Resources | G15: MEASURE 3.1; MANAGE 4.1 | H15: InfoSec / Internal Audit | I15: Not started | O15: 5 | P15: =IF(J15="","",O15*J15) | Q15: Play 11 | R15: ST-12 | S15: MAS M3.8 | MGF D3.6, D3.13 | V15: —
A16: S3 Auditability | B16: S3.2 | C16: Decision-record content | D16: Capture proposed action, rules applied, disposition, agent identity and timestamp per record | E16: Transparency (FEAT F4) | F16: A.8; A.9 | G16: MAP 1.1; MEASURE 3.1 | H16: InfoSec / Compliance | I16: Not started | O16: 4 | P16: =IF(J16="","",O16*J16) | Q16: Play 11 | R16: ST-12 | S16: MAS M3.3, F4 | MGF D2.7, D3.13 | V16: —
A17: S3 Auditability | B17: S3.3 | C17: Traceability to mandate & policy version | D17: Link each record to the controls-repository / mandate version that governed the action | E17: Accountability (FEAT F3) | F17: A.6; A.2 AI policy | G17: GOVERN 1.3; MEASURE 3.1 | H17: AI Risk (2nd line) | I17: Not started | O17: 4 | P17: =IF(J17="","",O17*J17) | Q17: Play 8, 11 | S17: MAS F3 | MGF D1.5 | V17: —
A18: S3 Auditability | B18: S3.4 | C18: Supervisory & audit evidence | D18: Make logs retrievable for internal audit, compliance and MAS supervisory review | E18: Records & Auditability | F18: A.8; A.9 | G18: GOVERN 1.1; MEASURE 3.1 | H18: Compliance & Legal / Internal Audit | I18: Not started | O18: 4 | P18: =IF(J18="","",O18*J18) | Q18: Play 8, 11 | R18: ST-12 | S18: MAS M3.8 | MGF D3.13 | V18: PA 6
A19: S3 Auditability | B19: S3.5 | C19: Review of flagged actions | D19: Ensure proceed-and-flag items are actually reviewed and dispositioned post-hoc | E19: Monitoring | F19: A.6 AI system life cycle | G19: MEASURE 4.1; MANAGE 4.1 | H19: AI Risk (2nd line) / Model Owner | I19: Not started | O19: 4 | P19: =IF(J19="","",O19*J19) | Q19: Play 5, 6 | S19: MAS M3.10 | MGF D2.5, D3.14, D3.15 | V19: —
A20: S4 Interoperability | B20: S4.1 | C20: Integration-model selection | D20: Document native-embedding vs. gateway-interception choice per agent / system | E20: Lifecycle: Deployment | F20: A.6; A.4 Resources | G20: MAP 1.1; MANAGE 2.4 | H20: InfoSec / Technology | I20: Not started | O20: 3 | P20: =IF(J20="","",O20*J20) | Q20: Play 3, 11 | S20: MAS M3.5 | V20: —
A21: S4 Interoperability | B21: S4.2 | C21: Gateway interception of actions | D21: Provide an API-level chokepoint that intercepts outbound agent actions where native embedding isn't feasible | E21: Governance & Oversight | F21: A.9 Use of AI systems | G21: MANAGE 2.3, 2.4 | H21: InfoSec / Technology | I21: Not started | O21: 4 | P21: =IF(J21="","",O21*J21) | Q21: Play 11 | R21: ST-14 | S21: MAS M3.7 | MGF D3.1 | V21: PA 8
A22: S4 Interoperability | B22: S4.3 | C22: Standard governance-record schema | D22: Adopt a portable, consistent record schema across agents and systems | E22: Transparency (FEAT F4) | F22: A.8 Information for interested parties | G22: MAP 1.1; MEASURE 3.1 | H22: InfoSec / AI Risk (2nd line) | I22: Not started | O22: 3 | P22: =IF(J22="","",O22*J22) | Q22: Play 11 | S22: MAS M3.8 | V22: —
A23: S4 Interoperability | B23: S4.4 | C23: Cross-system enforcement consistency | D23: Enforce the same mandate and policy regardless of the downstream system acted upon | E23: Governance & Oversight | F23: A.9; A.6 | G23: GOVERN 1.3; MANAGE 2.3 | H23: AI Risk (2nd line) | I23: Not started | O23: 4 | P23: =IF(J23="","",O23*J23) | Q23: Play 11 | R23: ST-14 | S23: MAS M3.14 | MGF D1.6, D3.9 | V23: —
A24: S4 Interoperability | B24: S4.5 | C24: Third-party / vendor agent coverage | D24: Subject externally-sourced agents to the same runtime checks and logging | E24: Third-Party Risk | F24: A.10 Third-party; A.9 | G24: GOVERN 3.2; MANAGE 3.1 | H24: AI Risk (2nd line) / Compliance | I24: Not started | O24: 4 | P24: =IF(J24="","",O24*J24) | Q24: Play 7, 11 | R24: ST-14 | S24: MAS M3.14 | MGF D1.6 | V24: PA 3
A26: ★ = load-bearing SAFR safeguard. Weight = criticality (seeded default — tune to risk appetite). Weighted maturity = Weight × Maturity.
A27: Basis: SAFR white paper (MAS / BuildFin.ai, 3 Jul 2026) — four safeguard principles (policy-bound execution, real-time validation, auditability, interoperability) and four components (agent identity, controls repository, disposition engine, audit log). Control IDs S1–S4 are this playbook's working derivations, not MAS-issued numbered controls. ISO / NIST / MAS mappings are section / function-level and should be reconciled against the primary PDF and your Control Library IDs before external use.

Sheet CSA Priority-Action Crosswalk
A1: CSA Priority-Action Crosswalk — mapped to Playbook control IDs
A3: CSA Priority Action | B3: What it requires | C3: CSA source refs (OWASP / ATLAS / NIST CSF 2.0) | D3: MAS (M / F) | E3: MGF Agentic (D) | F3: SAFR (S) | G3: Fit | H3: Scope / 2LoD challenge note
A4: PA 1 · Point Agents at Your Code & Pipelines | B4: Turn agents inward — run LLM security review across own code and CI/CD before merge; shift left into developers' coding agents. | C4: LLM01, LLM05, LLM08, ASI01, AML.T0018, AML.T0051.001, PR.PS, ID.IM | D4: M3.6, M3.7 | E4: D3.8, D3.9 | F4: — | G4: Partial | H4: A practice, not a control. The Playbook governs the review agent itself (D1.4 least-privilege, D3.2 sandbox), not the act of scanning.
A5: PA 2 · Require AI Agent Adoption | B5: Formalise and mandate agent use across security functions with mandatory controls and oversight; optional programs don't overcome cultural barriers. | C5: GV.OC, GV.RM, DE.CM, RS.MA | D5: M1.1, M1.2, M1.5, M2.1, M2.2 | E5: D2.1 | F5: — | G5: Core | H5: Adoption sits behind the governance + inventory gate — mandate is not ungoverned rollout.
A6: PA 3 · Defend Your Agents | B6: Treat agents as privileged, insecure-by-default; audit the harness (prompts, tools, retrieval, escalation); bound scope, blast radius and human override; secure the agentic supply chain (MCP, extensions, skills). | C6: LLM06, ASI02, ASI03, AML.T0047, PR.AA, GV.SC | D6: M3.15, M3.14, M3.7 | E6: D1.3, D1.4, D1.5, D1.6, D3.1, D3.2, D3.3, D3.7, D3.11 | F6: S1.1, S1.2, S1.4, S2.3, S4.5 | G6: Core | H6: The register's centre of gravity — spans most of D1/D3 and S1/S4. Agentic supply chain = D1.6 / M3.14 / S4.5.
A7: PA 4 · Establish Innovation, Acceleration Governance | B7: Cross-functional Security / Legal / Engineering forum to evaluate threats and fast-track defensive-tech onboarding. | C7: GV.OC, GV.RM, GV.RR, GV.OV | D7: M1.3, M1.4 | E7: D2.2 | F7: — | G7: Core | H7: 2LoD tension — acceleration (D2.2 adaptive governance) must stay bounded by M1.4 risk appetite; speed does not dissolve the approval gate.
A8: PA 5 · Prepare for Continuous Patching | B8: Build triage and deployment capacity for a potential flood of patches as Glasswing-driven disclosures land. | C8: AML.T0040, AML.T0043, PR.PS, PR.IR | D8: M3.12, M4.2 | E8: D3.10 | F8: — | G8: Partial | H8: AI-slice only (model / agent updates). Estate-wide patch and vulnerability management lives in MAS TRM, not this Playbook.
A9: PA 6 · Update Risk Models & Reporting | B9: Update metrics, reporting and business-risk calculations to reflect AI-accelerated exploit timelines; communicate the shift to stakeholders. | C9: GV.OC, GV.RM, RS.CO | D9: M2.3, M2.4, M3.10, M1.1 | E9: D2.5 | F9: S3.4 | G9: Core | H9: Your 2LoD seat; the Maturity Dashboard is the instrument. Ratings should track live residual exposure, not remediation paperwork.
A10: PA 7 · Inventory & Reduce Attack Surface | B10: Build / maintain a continuous inventory, generate real SBOMs, decommission unneeded functionality, isolate or air-gap at-risk systems. | C10: ASI04, AML.T0000, ID.AM, GV.SC | D10: M2.1, M2.2, M3.13 | E10: D1.1, D1.6 | F10: — | G10: Core | H10: Inventory (M2.2) + safe decommission (M3.13); software / dependency SBOM via M3.14 / D1.6.
A11: PA 8 · Harden Your Environment | B11: Egress filtering, deep segmentation, zero trust, dependency lockdown, phishing-resistant MFA, software minimisation. | C11: PR.IR, PR.PS | D11: M3.7 | E11: D3.1, D3.2, D3.3, D3.7 | F11: S4.2 | G11: Partial | H11: AI-slice only. Classic network / MFA / segmentation hardening sits in MAS TRM. S4.2 gateway interception = the agent-action enforcement point.
A12: PA 9 · Build a Deception Capability | B12: Deploy canaries and honey tokens, layer behavioural monitoring, pre-authorise containment, build machine-speed response playbooks. | C12: ASI08, DE.CM, DE.AE, RS.MA | D12: — | E12: D3.11, D3.12 | F12: S2.5 | G12: Partial | H12: Only the anomaly-detection / monitoring slice maps (D3.12). Deception tooling itself is out of Playbook scope.
A13: PA 10 · Build an Automated Response Capability | B13: Make detection engineering and IR systemic and, where possible, autonomous — pre-authorised containment and machine-speed playbooks. | C13: ASI08, AML.T0047, DE.CM, DE.AE, RS.MA | D13: M3.11 | E13: D3.16, D3.11, D2.6 | F13: S2.1, S2.3, S2.4 | G13: Core | H13: Automated containment (S2.1 / S2.4) is only defensible with human-in-the-loop escalation (S2.3) and automation-bias countermeasures (D2.6) live — otherwise it is an uncontrolled action.
A14: PA 11 · Stand Up VulnOps | B14: Build a permanent Vulnerability Operations function — staffed and automated like DevOps — owning continuous zero-day discovery and automated remediation across the estate. | C14: ASI10, ASI06, AML.T0018, ID.RA, ID.AM, DE.CM | D14: M3.6, M3.7, M4.1, M4.2 | E14: D3.8, D3.15 | F14: — | G14: Partial | H14: AI-slice only (agent testing D3.8, periodic audit D3.15, capacity M4.1 / M4.2). VulnOps as an enterprise function lives in the cyber control set.
A16: Fit — Core = the Playbook is the natural home for this action; Partial = only the AI / agentic slice maps here, the estate-wide capability lives in MAS TRM or the cyber control set.
A17: CSA source refs — framework anchors from the CSA risk-register row(s) mapping to each action: OWASP LLM Top 10 2025 (LLM..), OWASP Agentic Top 10 2026 (ASI..), MITRE ATLAS (AML.T..), NIST CSF 2.0 (GV / ID / PR / DE / RS).
A18: Playbook control IDs — verified against this workbook (MAS M/F, MGF Agentic D, SAFR S). M-series traces to AIRG Consultation Paper P017-2025 (consultation, not issued Guidelines); D = IMDA MGF for Agentic AI (issued); S = SAFR white paper (MAS / BuildFin.ai, 3 Jul 2026). ISO 42001 / NIST AI RMF anchors ride along inside each D-row and S-row.
A19: Source — CSA / SANS / [un]prompted / OWASP GenAI, "The AI Vulnerability Storm: Building a Mythos-ready Security Program", v0.95 DRAFT, 18 Apr 2026 (CC BY-NC 4.0). Priority-action table is draft-stage and assumes an aggressive timetable — treat as candidate actions.
